{"$schema":"http://cyclonedx.org/schema/bom-1.6.schema.json","bomFormat":"CycloneDX","specVersion":"1.6","serialNumber":"urn:uuid:baf2147b-cbe6-4406-95a6-50383385fcd8","version":1,"metadata":{"timestamp":"2025-11-11T22:00:32+01:00","tools":{"components":[{"type":"application","author":"anchore","name":"syft","version":"1.37.0"}]},"component":{"bom-ref":"c833373750aa5a2d","type":"file","name":"grc-frontend-portal"}},"components":[{"bom-ref":"pkg:npm/%40emnapi/runtime@1.7.0?package-id=41aa54b22d8fd7ea","type":"library","name":"@emnapi/runtime","version":"1.7.0","licenses":[{"license":{"id":"MIT"}}],"cpe":"cpe:2.3:a:\\@emnapi\\/runtime:\\@emnapi\\/runtime:1.7.0:*:*:*:*:*:*:*","purl":"pkg:npm/%40emnapi/runtime@1.7.0","properties":[{"name":"syft:package:foundBy","value":"javascript-lock-cataloger"},{"name":"syft:package:language","value":"javascript"},{"name":"syft:package:type","value":"npm"},{"name":"syft:package:metadataType","value":"javascript-npm-package-lock-entry"},{"name":"syft:location:0:path","value":"/package-lock.json"}]},{"bom-ref":"pkg:npm/%40img/colour@1.0.0?package-id=ff480579726b30fc","type":"library","name":"@img/colour","version":"1.0.0","licenses":[{"license":{"id":"MIT"}}],"cpe":"cpe:2.3:a:\\@img\\/colour:\\@img\\/colour:1.0.0:*:*:*:*:*:*:*","purl":"pkg:npm/%40img/colour@1.0.0","properties":[{"name":"syft:package:foundBy","value":"javascript-lock-cataloger"},{"name":"syft:package:language","value":"javascript"},{"name":"syft:package:type","value":"npm"},{"name":"syft:package:metadataType","value":"javascript-npm-package-lock-entry"},{"name":"syft:location:0:path","value":"/package-lock.json"}]},{"bom-ref":"pkg:npm/%40img/sharp-darwin-arm64@0.34.5?package-id=c848e29115ff698b","type":"library","name":"@img/sharp-darwin-arm64","version":"0.34.5","licenses":[{"license":{"id":"Apache-2.0"}}],"cpe":"cpe:2.3:a:\\@img\\/sharp-darwin-arm64:\\@img\\/sharp-darwin-arm64:0.34.5:*:*:*:*:*:*:*","purl":"pkg:npm/%40img/sharp-darwin-arm64@0.34.5","properties":[{"name":"syft:package:foundBy","value":"javascript-lock-cataloger"},{"name":"syft:package:language","value":"javascript"},{"name":"syft:package:type","value":"npm"},{"name":"syft:package:metadataType","value":"javascript-npm-package-lock-entry"},{"name":"syft:cpe23","value":"cpe:2.3:a:\\@img\\/sharp-darwin-arm64:\\@img\\/sharp_darwin_arm64:0.34.5:*:*:*:*:*:*:*"},{"name":"syft:cpe23","value":"cpe:2.3:a:\\@img\\/sharp_darwin_arm64:\\@img\\/sharp-darwin-arm64:0.34.5:*:*:*:*:*:*:*"},{"name":"syft:cpe23","value":"cpe:2.3:a:\\@img\\/sharp_darwin_arm64:\\@img\\/sharp_darwin_arm64:0.34.5:*:*:*:*:*:*:*"},{"name":"syft:cpe23","value":"cpe:2.3:a:\\@img\\/sharp-darwin:\\@img\\/sharp-darwin-arm64:0.34.5:*:*:*:*:*:*:*"},{"name":"syft:cpe23","value":"cpe:2.3:a:\\@img\\/sharp-darwin:\\@img\\/sharp_darwin_arm64:0.34.5:*:*:*:*:*:*:*"},{"name":"syft:cpe23","value":"cpe:2.3:a:\\@img\\/sharp_darwin:\\@img\\/sharp-darwin-arm64:0.34.5:*:*:*:*:*:*:*"},{"name":"syft:cpe23","value":"cpe:2.3:a:\\@img\\/sharp_darwin:\\@img\\/sharp_darwin_arm64:0.34.5:*:*:*:*:*:*:*"},{"name":"syft:cpe23","value":"cpe:2.3:a:\\@img\\/sharp:\\@img\\/sharp-darwin-arm64:0.34.5:*:*:*:*:*:*:*"},{"name":"syft:cpe23","value":"cpe:2.3:a:\\@img\\/sharp:\\@img\\/sharp_darwin_arm64:0.34.5:*:*:*:*:*:*:*"},{"name":"syft:location:0:path","value":"/package-lock.json"}]},{"bom-ref":"pkg:npm/%40img/sharp-darwin-x64@0.34.5?package-id=e104eff3af96ba12","type":"library","name":"@img/sharp-darwin-x64","version":"0.34.5","licenses":[{"license":{"id":"Apache-2.0"}}],"cpe":"cpe:2.3:a:\\@img\\/sharp-darwin-x64:\\@img\\/sharp-darwin-x64:0.34.5:*:*:*:*:*:*:*","purl":"pkg:npm/%40img/sharp-darwin-x64@0.34.5","properties":[{"name":"syft:package:foundBy","value":"javascript-lock-cataloger"},{"name":"syft:package:language","value":"javascript"},{"name":"syft:package:type","value":"npm"},{"name":"syft:package:metadataType","value":"javascript-npm-package-lock-entry"},{"name":"syft:cpe23","value":"cpe:2.3:a:\\@img\\/sharp-darwin-x64:\\@img\\/sharp_darwin_x64:0.34.5:*:*:*:*:*:*:*"},{"name":"syft:cpe23","value":"cpe:2.3:a:\\@img\\/sharp_darwin_x64:\\@img\\/sharp-darwin-x64:0.34.5:*:*:*:*:*:*:*"},{"name":"syft:cpe23","value":"cpe:2.3:a:\\@img\\/sharp_darwin_x64:\\@img\\/sharp_darwin_x64:0.34.5:*:*:*:*:*:*:*"},{"name":"syft:cpe23","value":"cpe:2.3:a:\\@img\\/sharp-darwin:\\@img\\/sharp-darwin-x64:0.34.5:*:*:*:*:*:*:*"},{"name":"syft:cpe23","value":"cpe:2.3:a:\\@img\\/sharp-darwin:\\@img\\/sharp_darwin_x64:0.34.5:*:*:*:*:*:*:*"},{"name":"syft:cpe23","value":"cpe:2.3:a:\\@img\\/sharp_darwin:\\@img\\/sharp-darwin-x64:0.34.5:*:*:*:*:*:*:*"},{"name":"syft:cpe23","value":"cpe:2.3:a:\\@img\\/sharp_darwin:\\@img\\/sharp_darwin_x64:0.34.5:*:*:*:*:*:*:*"},{"name":"syft:cpe23","value":"cpe:2.3:a:\\@img\\/sharp:\\@img\\/sharp-darwin-x64:0.34.5:*:*:*:*:*:*:*"},{"name":"syft:cpe23","value":"cpe:2.3:a:\\@img\\/sharp:\\@img\\/sharp_darwin_x64:0.34.5:*:*:*:*:*:*:*"},{"name":"syft:location:0:path","value":"/package-lock.json"}]},{"bom-ref":"pkg:npm/%40img/sharp-libvips-darwin-arm64@1.2.4?package-id=c89fc530d813f023","type":"library","name":"@img/sharp-libvips-darwin-arm64","version":"1.2.4","licenses":[{"license":{"id":"LGPL-3.0-or-later"}}],"cpe":"cpe:2.3:a:\\@img\\/sharp-libvips-darwin-arm64:\\@img\\/sharp-libvips-darwin-arm64:1.2.4:*:*:*:*:*:*:*","purl":"pkg:npm/%40img/sharp-libvips-darwin-arm64@1.2.4","properties":[{"name":"syft:package:foundBy","value":"javascript-lock-cataloger"},{"name":"syft:package:language","value":"javascript"},{"name":"syft:package:type","value":"npm"},{"name":"syft:package:metadataType","value":"javascript-npm-package-lock-entry"},{"name":"syft:cpe23","value":"cpe:2.3:a:\\@img\\/sharp-libvips-darwin-arm64:\\@img\\/sharp_libvips_darwin_arm64:1.2.4:*:*:*:*:*:*:*"},{"name":"syft:cpe23","value":"cpe:2.3:a:\\@img\\/sharp_libvips_darwin_arm64:\\@img\\/sharp-libvips-darwin-arm64:1.2.4:*:*:*:*:*:*:*"},{"name":"syft:cpe23","value":"cpe:2.3:a:\\@img\\/sharp_libvips_darwin_arm64:\\@img\\/sharp_libvips_darwin_arm64:1.2.4:*:*:*:*:*:*:*"},{"name":"syft:cpe23","value":"cpe:2.3:a:\\@img\\/sharp-libvips-darwin:\\@img\\/sharp-libvips-darwin-arm64:1.2.4:*:*:*:*:*:*:*"},{"name":"syft:cpe23","value":"cpe:2.3:a:\\@img\\/sharp-libvips-darwin:\\@img\\/sharp_libvips_darwin_arm64:1.2.4:*:*:*:*:*:*:*"},{"name":"syft:cpe23","value":"cpe:2.3:a:\\@img\\/sharp_libvips_darwin:\\@img\\/sharp-libvips-darwin-arm64:1.2.4:*:*:*:*:*:*:*"},{"name":"syft:cpe23","value":"cpe:2.3:a:\\@img\\/sharp_libvips_darwin:\\@img\\/sharp_libvips_darwin_arm64:1.2.4:*:*:*:*:*:*:*"},{"name":"syft:cpe23","value":"cpe:2.3:a:\\@img\\/sharp-libvips:\\@img\\/sharp-libvips-darwin-arm64:1.2.4:*:*:*:*:*:*:*"},{"name":"syft:cpe23","value":"cpe:2.3:a:\\@img\\/sharp-libvips:\\@img\\/sharp_libvips_darwin_arm64:1.2.4:*:*:*:*:*:*:*"},{"name":"syft:cpe23","value":"cpe:2.3:a:\\@img\\/sharp_libvips:\\@img\\/sharp-libvips-darwin-arm64:1.2.4:*:*:*:*:*:*:*"},{"name":"syft:cpe23","value":"cpe:2.3:a:\\@img\\/sharp_libvips:\\@img\\/sharp_libvips_darwin_arm64:1.2.4:*:*:*:*:*:*:*"},{"name":"syft:cpe23","value":"cpe:2.3:a:\\@img\\/sharp:\\@img\\/sharp-libvips-darwin-arm64:1.2.4:*:*:*:*:*:*:*"},{"name":"syft:cpe23","value":"cpe:2.3:a:\\@img\\/sharp:\\@img\\/sharp_libvips_darwin_arm64:1.2.4:*:*:*:*:*:*:*"},{"name":"syft:location:0:path","value":"/package-lock.json"}]},{"bom-ref":"pkg:npm/%40img/sharp-libvips-darwin-x64@1.2.4?package-id=9334bee5692d8dd8","type":"library","name":"@img/sharp-libvips-darwin-x64","version":"1.2.4","licenses":[{"license":{"id":"LGPL-3.0-or-later"}}],"cpe":"cpe:2.3:a:\\@img\\/sharp-libvips-darwin-x64:\\@img\\/sharp-libvips-darwin-x64:1.2.4:*:*:*:*:*:*:*","purl":"pkg:npm/%40img/sharp-libvips-darwin-x64@1.2.4","properties":[{"name":"syft:package:foundBy","value":"javascript-lock-cataloger"},{"name":"syft:package:language","value":"javascript"},{"name":"syft:package:type","value":"npm"},{"name":"syft:package:metadataType","value":"javascript-npm-package-lock-entry"},{"name":"syft:cpe23","value":"cpe:2.3:a:\\@img\\/sharp-libvips-darwin-x64:\\@img\\/sharp_libvips_darwin_x64:1.2.4:*:*:*:*:*:*:*"},{"name":"syft:cpe23","value":"cpe:2.3:a:\\@img\\/sharp_libvips_darwin_x64:\\@img\\/sharp-libvips-darwin-x64:1.2.4:*:*:*:*:*:*:*"},{"name":"syft:cpe23","value":"cpe:2.3:a:\\@img\\/sharp_libvips_darwin_x64:\\@img\\/sharp_libvips_darwin_x64:1.2.4:*:*:*:*:*:*:*"},{"name":"syft:cpe23","value":"cpe:2.3:a:\\@img\\/sharp-libvips-darwin:\\@img\\/sharp-libvips-darwin-x64:1.2.4:*:*:*:*:*:*:*"},{"name":"syft:cpe23","value":"cpe:2.3:a:\\@img\\/sharp-libvips-darwin:\\@img\\/sharp_libvips_darwin_x64:1.2.4:*:*:*:*:*:*:*"},{"name":"syft:cpe23","value":"cpe:2.3:a:\\@img\\/sharp_libvips_darwin:\\@img\\/sharp-libvips-darwin-x64:1.2.4:*:*:*:*:*:*:*"},{"name":"syft:cpe23","value":"cpe:2.3:a:\\@img\\/sharp_libvips_darwin:\\@img\\/sharp_libvips_darwin_x64:1.2.4:*:*:*:*:*:*:*"},{"name":"syft:cpe23","value":"cpe:2.3:a:\\@img\\/sharp-libvips:\\@img\\/sharp-libvips-darwin-x64:1.2.4:*:*:*:*:*:*:*"},{"name":"syft:cpe23","value":"cpe:2.3:a:\\@img\\/sharp-libvips:\\@img\\/sharp_libvips_darwin_x64:1.2.4:*:*:*:*:*:*:*"},{"name":"syft:cpe23","value":"cpe:2.3:a:\\@img\\/sharp_libvips:\\@img\\/sharp-libvips-darwin-x64:1.2.4:*:*:*:*:*:*:*"},{"name":"syft:cpe23","value":"cpe:2.3:a:\\@img\\/sharp_libvips:\\@img\\/sharp_libvips_darwin_x64:1.2.4:*:*:*:*:*:*:*"},{"name":"syft:cpe23","value":"cpe:2.3:a:\\@img\\/sharp:\\@img\\/sharp-libvips-darwin-x64:1.2.4:*:*:*:*:*:*:*"},{"name":"syft:cpe23","value":"cpe:2.3:a:\\@img\\/sharp:\\@img\\/sharp_libvips_darwin_x64:1.2.4:*:*:*:*:*:*:*"},{"name":"syft:location:0:path","value":"/package-lock.json"}]},{"bom-ref":"pkg:npm/%40img/sharp-libvips-linux-arm@1.2.4?package-id=27e73df3ed720af1","type":"library","name":"@img/sharp-libvips-linux-arm","version":"1.2.4","licenses":[{"license":{"id":"LGPL-3.0-or-later"}}],"cpe":"cpe:2.3:a:\\@img\\/sharp-libvips-linux-arm:\\@img\\/sharp-libvips-linux-arm:1.2.4:*:*:*:*:*:*:*","purl":"pkg:npm/%40img/sharp-libvips-linux-arm@1.2.4","properties":[{"name":"syft:package:foundBy","value":"javascript-lock-cataloger"},{"name":"syft:package:language","value":"javascript"},{"name":"syft:package:type","value":"npm"},{"name":"syft:package:metadataType","value":"javascript-npm-package-lock-entry"},{"name":"syft:cpe23","value":"cpe:2.3:a:\\@img\\/sharp-libvips-linux-arm:\\@img\\/sharp_libvips_linux_arm:1.2.4:*:*:*:*:*:*:*"},{"name":"syft:cpe23","value":"cpe:2.3:a:\\@img\\/sharp_libvips_linux_arm:\\@img\\/sharp-libvips-linux-arm:1.2.4:*:*:*:*:*:*:*"},{"name":"syft:cpe23","value":"cpe:2.3:a:\\@img\\/sharp_libvips_linux_arm:\\@img\\/sharp_libvips_linux_arm:1.2.4:*:*:*:*:*:*:*"},{"name":"syft:cpe23","value":"cpe:2.3:a:\\@img\\/sharp-libvips-linux:\\@img\\/sharp-libvips-linux-arm:1.2.4:*:*:*:*:*:*:*"},{"name":"syft:cpe23","value":"cpe:2.3:a:\\@img\\/sharp-libvips-linux:\\@img\\/sharp_libvips_linux_arm:1.2.4:*:*:*:*:*:*:*"},{"name":"syft:cpe23","value":"cpe:2.3:a:\\@img\\/sharp_libvips_linux:\\@img\\/sharp-libvips-linux-arm:1.2.4:*:*:*:*:*:*:*"},{"name":"syft:cpe23","value":"cpe:2.3:a:\\@img\\/sharp_libvips_linux:\\@img\\/sharp_libvips_linux_arm:1.2.4:*:*:*:*:*:*:*"},{"name":"syft:cpe23","value":"cpe:2.3:a:\\@img\\/sharp-libvips:\\@img\\/sharp-libvips-linux-arm:1.2.4:*:*:*:*:*:*:*"},{"name":"syft:cpe23","value":"cpe:2.3:a:\\@img\\/sharp-libvips:\\@img\\/sharp_libvips_linux_arm:1.2.4:*:*:*:*:*:*:*"},{"name":"syft:cpe23","value":"cpe:2.3:a:\\@img\\/sharp_libvips:\\@img\\/sharp-libvips-linux-arm:1.2.4:*:*:*:*:*:*:*"},{"name":"syft:cpe23","value":"cpe:2.3:a:\\@img\\/sharp_libvips:\\@img\\/sharp_libvips_linux_arm:1.2.4:*:*:*:*:*:*:*"},{"name":"syft:cpe23","value":"cpe:2.3:a:\\@img\\/sharp:\\@img\\/sharp-libvips-linux-arm:1.2.4:*:*:*:*:*:*:*"},{"name":"syft:cpe23","value":"cpe:2.3:a:\\@img\\/sharp:\\@img\\/sharp_libvips_linux_arm:1.2.4:*:*:*:*:*:*:*"},{"name":"syft:location:0:path","value":"/package-lock.json"}]},{"bom-ref":"pkg:npm/%40img/sharp-libvips-linux-arm64@1.2.4?package-id=2c75b7720416d38f","type":"library","name":"@img/sharp-libvips-linux-arm64","version":"1.2.4","licenses":[{"license":{"id":"LGPL-3.0-or-later"}}],"cpe":"cpe:2.3:a:\\@img\\/sharp-libvips-linux-arm64:\\@img\\/sharp-libvips-linux-arm64:1.2.4:*:*:*:*:*:*:*","purl":"pkg:npm/%40img/sharp-libvips-linux-arm64@1.2.4","properties":[{"name":"syft:package:foundBy","value":"javascript-lock-cataloger"},{"name":"syft:package:language","value":"javascript"},{"name":"syft:package:type","value":"npm"},{"name":"syft:package:metadataType","value":"javascript-npm-package-lock-entry"},{"name":"syft:cpe23","value":"cpe:2.3:a:\\@img\\/sharp-libvips-linux-arm64:\\@img\\/sharp_libvips_linux_arm64:1.2.4:*:*:*:*:*:*:*"},{"name":"syft:cpe23","value":"cpe:2.3:a:\\@img\\/sharp_libvips_linux_arm64:\\@img\\/sharp-libvips-linux-arm64:1.2.4:*:*:*:*:*:*:*"},{"name":"syft:cpe23","value":"cpe:2.3:a:\\@img\\/sharp_libvips_linux_arm64:\\@img\\/sharp_libvips_linux_arm64:1.2.4:*:*:*:*:*:*:*"},{"name":"syft:cpe23","value":"cpe:2.3:a:\\@img\\/sharp-libvips-linux:\\@img\\/sharp-libvips-linux-arm64:1.2.4:*:*:*:*:*:*:*"},{"name":"syft:cpe23","value":"cpe:2.3:a:\\@img\\/sharp-libvips-linux:\\@img\\/sharp_libvips_linux_arm64:1.2.4:*:*:*:*:*:*:*"},{"name":"syft:cpe23","value":"cpe:2.3:a:\\@img\\/sharp_libvips_linux:\\@img\\/sharp-libvips-linux-arm64:1.2.4:*:*:*:*:*:*:*"},{"name":"syft:cpe23","value":"cpe:2.3:a:\\@img\\/sharp_libvips_linux:\\@img\\/sharp_libvips_linux_arm64:1.2.4:*:*:*:*:*:*:*"},{"name":"syft:cpe23","value":"cpe:2.3:a:\\@img\\/sharp-libvips:\\@img\\/sharp-libvips-linux-arm64:1.2.4:*:*:*:*:*:*:*"},{"name":"syft:cpe23","value":"cpe:2.3:a:\\@img\\/sharp-libvips:\\@img\\/sharp_libvips_linux_arm64:1.2.4:*:*:*:*:*:*:*"},{"name":"syft:cpe23","value":"cpe:2.3:a:\\@img\\/sharp_libvips:\\@img\\/sharp-libvips-linux-arm64:1.2.4:*:*:*:*:*:*:*"},{"name":"syft:cpe23","value":"cpe:2.3:a:\\@img\\/sharp_libvips:\\@img\\/sharp_libvips_linux_arm64:1.2.4:*:*:*:*:*:*:*"},{"name":"syft:cpe23","value":"cpe:2.3:a:\\@img\\/sharp:\\@img\\/sharp-libvips-linux-arm64:1.2.4:*:*:*:*:*:*:*"},{"name":"syft:cpe23","value":"cpe:2.3:a:\\@img\\/sharp:\\@img\\/sharp_libvips_linux_arm64:1.2.4:*:*:*:*:*:*:*"},{"name":"syft:location:0:path","value":"/package-lock.json"}]},{"bom-ref":"pkg:npm/%40img/sharp-libvips-linux-ppc64@1.2.4?package-id=d80cce411a3e883f","type":"library","name":"@img/sharp-libvips-linux-ppc64","version":"1.2.4","licenses":[{"license":{"id":"LGPL-3.0-or-later"}}],"cpe":"cpe:2.3:a:\\@img\\/sharp-libvips-linux-ppc64:\\@img\\/sharp-libvips-linux-ppc64:1.2.4:*:*:*:*:*:*:*","purl":"pkg:npm/%40img/sharp-libvips-linux-ppc64@1.2.4","properties":[{"name":"syft:package:foundBy","value":"javascript-lock-cataloger"},{"name":"syft:package:language","value":"javascript"},{"name":"syft:package:type","value":"npm"},{"name":"syft:package:metadataType","value":"javascript-npm-package-lock-entry"},{"name":"syft:cpe23","value":"cpe:2.3:a:\\@img\\/sharp-libvips-linux-ppc64:\\@img\\/sharp_libvips_linux_ppc64:1.2.4:*:*:*:*:*:*:*"},{"name":"syft:cpe23","value":"cpe:2.3:a:\\@img\\/sharp_libvips_linux_ppc64:\\@img\\/sharp-libvips-linux-ppc64:1.2.4:*:*:*:*:*:*:*"},{"name":"syft:cpe23","value":"cpe:2.3:a:\\@img\\/sharp_libvips_linux_ppc64:\\@img\\/sharp_libvips_linux_ppc64:1.2.4:*:*:*:*:*:*:*"},{"name":"syft:cpe23","value":"cpe:2.3:a:\\@img\\/sharp-libvips-linux:\\@img\\/sharp-libvips-linux-ppc64:1.2.4:*:*:*:*:*:*:*"},{"name":"syft:cpe23","value":"cpe:2.3:a:\\@img\\/sharp-libvips-linux:\\@img\\/sharp_libvips_linux_ppc64:1.2.4:*:*:*:*:*:*:*"},{"name":"syft:cpe23","value":"cpe:2.3:a:\\@img\\/sharp_libvips_linux:\\@img\\/sharp-libvips-linux-ppc64:1.2.4:*:*:*:*:*:*:*"},{"name":"syft:cpe23","value":"cpe:2.3:a:\\@img\\/sharp_libvips_linux:\\@img\\/sharp_libvips_linux_ppc64:1.2.4:*:*:*:*:*:*:*"},{"name":"syft:cpe23","value":"cpe:2.3:a:\\@img\\/sharp-libvips:\\@img\\/sharp-libvips-linux-ppc64:1.2.4:*:*:*:*:*:*:*"},{"name":"syft:cpe23","value":"cpe:2.3:a:\\@img\\/sharp-libvips:\\@img\\/sharp_libvips_linux_ppc64:1.2.4:*:*:*:*:*:*:*"},{"name":"syft:cpe23","value":"cpe:2.3:a:\\@img\\/sharp_libvips:\\@img\\/sharp-libvips-linux-ppc64:1.2.4:*:*:*:*:*:*:*"},{"name":"syft:cpe23","value":"cpe:2.3:a:\\@img\\/sharp_libvips:\\@img\\/sharp_libvips_linux_ppc64:1.2.4:*:*:*:*:*:*:*"},{"name":"syft:cpe23","value":"cpe:2.3:a:\\@img\\/sharp:\\@img\\/sharp-libvips-linux-ppc64:1.2.4:*:*:*:*:*:*:*"},{"name":"syft:cpe23","value":"cpe:2.3:a:\\@img\\/sharp:\\@img\\/sharp_libvips_linux_ppc64:1.2.4:*:*:*:*:*:*:*"},{"name":"syft:location:0:path","value":"/package-lock.json"}]},{"bom-ref":"pkg:npm/%40img/sharp-libvips-linux-riscv64@1.2.4?package-id=52e557ca23c20a3e","type":"library","name":"@img/sharp-libvips-linux-riscv64","version":"1.2.4","licenses":[{"license":{"id":"LGPL-3.0-or-later"}}],"cpe":"cpe:2.3:a:\\@img\\/sharp-libvips-linux-riscv64:\\@img\\/sharp-libvips-linux-riscv64:1.2.4:*:*:*:*:*:*:*","purl":"pkg:npm/%40img/sharp-libvips-linux-riscv64@1.2.4","properties":[{"name":"syft:package:foundBy","value":"javascript-lock-cataloger"},{"name":"syft:package:language","value":"javascript"},{"name":"syft:package:type","value":"npm"},{"name":"syft:package:metadataType","value":"javascript-npm-package-lock-entry"},{"name":"syft:cpe23","value":"cpe:2.3:a:\\@img\\/sharp-libvips-linux-riscv64:\\@img\\/sharp_libvips_linux_riscv64:1.2.4:*:*:*:*:*:*:*"},{"name":"syft:cpe23","value":"cpe:2.3:a:\\@img\\/sharp_libvips_linux_riscv64:\\@img\\/sharp-libvips-linux-riscv64:1.2.4:*:*:*:*:*:*:*"},{"name":"syft:cpe23","value":"cpe:2.3:a:\\@img\\/sharp_libvips_linux_riscv64:\\@img\\/sharp_libvips_linux_riscv64:1.2.4:*:*:*:*:*:*:*"},{"name":"syft:cpe23","value":"cpe:2.3:a:\\@img\\/sharp-libvips-linux:\\@img\\/sharp-libvips-linux-riscv64:1.2.4:*:*:*:*:*:*:*"},{"name":"syft:cpe23","value":"cpe:2.3:a:\\@img\\/sharp-libvips-linux:\\@img\\/sharp_libvips_linux_riscv64:1.2.4:*:*:*:*:*:*:*"},{"name":"syft:cpe23","value":"cpe:2.3:a:\\@img\\/sharp_libvips_linux:\\@img\\/sharp-libvips-linux-riscv64:1.2.4:*:*:*:*:*:*:*"},{"name":"syft:cpe23","value":"cpe:2.3:a:\\@img\\/sharp_libvips_linux:\\@img\\/sharp_libvips_linux_riscv64:1.2.4:*:*:*:*:*:*:*"},{"name":"syft:cpe23","value":"cpe:2.3:a:\\@img\\/sharp-libvips:\\@img\\/sharp-libvips-linux-riscv64:1.2.4:*:*:*:*:*:*:*"},{"name":"syft:cpe23","value":"cpe:2.3:a:\\@img\\/sharp-libvips:\\@img\\/sharp_libvips_linux_riscv64:1.2.4:*:*:*:*:*:*:*"},{"name":"syft:cpe23","value":"cpe:2.3:a:\\@img\\/sharp_libvips:\\@img\\/sharp-libvips-linux-riscv64:1.2.4:*:*:*:*:*:*:*"},{"name":"syft:cpe23","value":"cpe:2.3:a:\\@img\\/sharp_libvips:\\@img\\/sharp_libvips_linux_riscv64:1.2.4:*:*:*:*:*:*:*"},{"name":"syft:cpe23","value":"cpe:2.3:a:\\@img\\/sharp:\\@img\\/sharp-libvips-linux-riscv64:1.2.4:*:*:*:*:*:*:*"},{"name":"syft:cpe23","value":"cpe:2.3:a:\\@img\\/sharp:\\@img\\/sharp_libvips_linux_riscv64:1.2.4:*:*:*:*:*:*:*"},{"name":"syft:location:0:path","value":"/package-lock.json"}]},{"bom-ref":"pkg:npm/%40img/sharp-libvips-linux-s390x@1.2.4?package-id=81d883c4287ffcd6","type":"library","name":"@img/sharp-libvips-linux-s390x","version":"1.2.4","licenses":[{"license":{"id":"LGPL-3.0-or-later"}}],"cpe":"cpe:2.3:a:\\@img\\/sharp-libvips-linux-s390x:\\@img\\/sharp-libvips-linux-s390x:1.2.4:*:*:*:*:*:*:*","purl":"pkg:npm/%40img/sharp-libvips-linux-s390x@1.2.4","properties":[{"name":"syft:package:foundBy","value":"javascript-lock-cataloger"},{"name":"syft:package:language","value":"javascript"},{"name":"syft:package:type","value":"npm"},{"name":"syft:package:metadataType","value":"javascript-npm-package-lock-entry"},{"name":"syft:cpe23","value":"cpe:2.3:a:\\@img\\/sharp-libvips-linux-s390x:\\@img\\/sharp_libvips_linux_s390x:1.2.4:*:*:*:*:*:*:*"},{"name":"syft:cpe23","value":"cpe:2.3:a:\\@img\\/sharp_libvips_linux_s390x:\\@img\\/sharp-libvips-linux-s390x:1.2.4:*:*:*:*:*:*:*"},{"name":"syft:cpe23","value":"cpe:2.3:a:\\@img\\/sharp_libvips_linux_s390x:\\@img\\/sharp_libvips_linux_s390x:1.2.4:*:*:*:*:*:*:*"},{"name":"syft:cpe23","value":"cpe:2.3:a:\\@img\\/sharp-libvips-linux:\\@img\\/sharp-libvips-linux-s390x:1.2.4:*:*:*:*:*:*:*"},{"name":"syft:cpe23","value":"cpe:2.3:a:\\@img\\/sharp-libvips-linux:\\@img\\/sharp_libvips_linux_s390x:1.2.4:*:*:*:*:*:*:*"},{"name":"syft:cpe23","value":"cpe:2.3:a:\\@img\\/sharp_libvips_linux:\\@img\\/sharp-libvips-linux-s390x:1.2.4:*:*:*:*:*:*:*"},{"name":"syft:cpe23","value":"cpe:2.3:a:\\@img\\/sharp_libvips_linux:\\@img\\/sharp_libvips_linux_s390x:1.2.4:*:*:*:*:*:*:*"},{"name":"syft:cpe23","value":"cpe:2.3:a:\\@img\\/sharp-libvips:\\@img\\/sharp-libvips-linux-s390x:1.2.4:*:*:*:*:*:*:*"},{"name":"syft:cpe23","value":"cpe:2.3:a:\\@img\\/sharp-libvips:\\@img\\/sharp_libvips_linux_s390x:1.2.4:*:*:*:*:*:*:*"},{"name":"syft:cpe23","value":"cpe:2.3:a:\\@img\\/sharp_libvips:\\@img\\/sharp-libvips-linux-s390x:1.2.4:*:*:*:*:*:*:*"},{"name":"syft:cpe23","value":"cpe:2.3:a:\\@img\\/sharp_libvips:\\@img\\/sharp_libvips_linux_s390x:1.2.4:*:*:*:*:*:*:*"},{"name":"syft:cpe23","value":"cpe:2.3:a:\\@img\\/sharp:\\@img\\/sharp-libvips-linux-s390x:1.2.4:*:*:*:*:*:*:*"},{"name":"syft:cpe23","value":"cpe:2.3:a:\\@img\\/sharp:\\@img\\/sharp_libvips_linux_s390x:1.2.4:*:*:*:*:*:*:*"},{"name":"syft:location:0:path","value":"/package-lock.json"}]},{"bom-ref":"pkg:npm/%40img/sharp-libvips-linux-x64@1.2.4?package-id=2bcd950592904a46","type":"library","name":"@img/sharp-libvips-linux-x64","version":"1.2.4","licenses":[{"license":{"id":"LGPL-3.0-or-later"}}],"cpe":"cpe:2.3:a:\\@img\\/sharp-libvips-linux-x64:\\@img\\/sharp-libvips-linux-x64:1.2.4:*:*:*:*:*:*:*","purl":"pkg:npm/%40img/sharp-libvips-linux-x64@1.2.4","properties":[{"name":"syft:package:foundBy","value":"javascript-lock-cataloger"},{"name":"syft:package:language","value":"javascript"},{"name":"syft:package:type","value":"npm"},{"name":"syft:package:metadataType","value":"javascript-npm-package-lock-entry"},{"name":"syft:cpe23","value":"cpe:2.3:a:\\@img\\/sharp-libvips-linux-x64:\\@img\\/sharp_libvips_linux_x64:1.2.4:*:*:*:*:*:*:*"},{"name":"syft:cpe23","value":"cpe:2.3:a:\\@img\\/sharp_libvips_linux_x64:\\@img\\/sharp-libvips-linux-x64:1.2.4:*:*:*:*:*:*:*"},{"name":"syft:cpe23","value":"cpe:2.3:a:\\@img\\/sharp_libvips_linux_x64:\\@img\\/sharp_libvips_linux_x64:1.2.4:*:*:*:*:*:*:*"},{"name":"syft:cpe23","value":"cpe:2.3:a:\\@img\\/sharp-libvips-linux:\\@img\\/sharp-libvips-linux-x64:1.2.4:*:*:*:*:*:*:*"},{"name":"syft:cpe23","value":"cpe:2.3:a:\\@img\\/sharp-libvips-linux:\\@img\\/sharp_libvips_linux_x64:1.2.4:*:*:*:*:*:*:*"},{"name":"syft:cpe23","value":"cpe:2.3:a:\\@img\\/sharp_libvips_linux:\\@img\\/sharp-libvips-linux-x64:1.2.4:*:*:*:*:*:*:*"},{"name":"syft:cpe23","value":"cpe:2.3:a:\\@img\\/sharp_libvips_linux:\\@img\\/sharp_libvips_linux_x64:1.2.4:*:*:*:*:*:*:*"},{"name":"syft:cpe23","value":"cpe:2.3:a:\\@img\\/sharp-libvips:\\@img\\/sharp-libvips-linux-x64:1.2.4:*:*:*:*:*:*:*"},{"name":"syft:cpe23","value":"cpe:2.3:a:\\@img\\/sharp-libvips:\\@img\\/sharp_libvips_linux_x64:1.2.4:*:*:*:*:*:*:*"},{"name":"syft:cpe23","value":"cpe:2.3:a:\\@img\\/sharp_libvips:\\@img\\/sharp-libvips-linux-x64:1.2.4:*:*:*:*:*:*:*"},{"name":"syft:cpe23","value":"cpe:2.3:a:\\@img\\/sharp_libvips:\\@img\\/sharp_libvips_linux_x64:1.2.4:*:*:*:*:*:*:*"},{"name":"syft:cpe23","value":"cpe:2.3:a:\\@img\\/sharp:\\@img\\/sharp-libvips-linux-x64:1.2.4:*:*:*:*:*:*:*"},{"name":"syft:cpe23","value":"cpe:2.3:a:\\@img\\/sharp:\\@img\\/sharp_libvips_linux_x64:1.2.4:*:*:*:*:*:*:*"},{"name":"syft:location:0:path","value":"/package-lock.json"}]},{"bom-ref":"pkg:npm/%40img/sharp-libvips-linuxmusl-arm64@1.2.4?package-id=76a8704a9a8ca9a9","type":"library","name":"@img/sharp-libvips-linuxmusl-arm64","version":"1.2.4","licenses":[{"license":{"id":"LGPL-3.0-or-later"}}],"cpe":"cpe:2.3:a:\\@img\\/sharp-libvips-linuxmusl-arm64:\\@img\\/sharp-libvips-linuxmusl-arm64:1.2.4:*:*:*:*:*:*:*","purl":"pkg:npm/%40img/sharp-libvips-linuxmusl-arm64@1.2.4","properties":[{"name":"syft:package:foundBy","value":"javascript-lock-cataloger"},{"name":"syft:package:language","value":"javascript"},{"name":"syft:package:type","value":"npm"},{"name":"syft:package:metadataType","value":"javascript-npm-package-lock-entry"},{"name":"syft:cpe23","value":"cpe:2.3:a:\\@img\\/sharp-libvips-linuxmusl-arm64:\\@img\\/sharp_libvips_linuxmusl_arm64:1.2.4:*:*:*:*:*:*:*"},{"name":"syft:cpe23","value":"cpe:2.3:a:\\@img\\/sharp_libvips_linuxmusl_arm64:\\@img\\/sharp-libvips-linuxmusl-arm64:1.2.4:*:*:*:*:*:*:*"},{"name":"syft:cpe23","value":"cpe:2.3:a:\\@img\\/sharp_libvips_linuxmusl_arm64:\\@img\\/sharp_libvips_linuxmusl_arm64:1.2.4:*:*:*:*:*:*:*"},{"name":"syft:cpe23","value":"cpe:2.3:a:\\@img\\/sharp-libvips-linuxmusl:\\@img\\/sharp-libvips-linuxmusl-arm64:1.2.4:*:*:*:*:*:*:*"},{"name":"syft:cpe23","value":"cpe:2.3:a:\\@img\\/sharp-libvips-linuxmusl:\\@img\\/sharp_libvips_linuxmusl_arm64:1.2.4:*:*:*:*:*:*:*"},{"name":"syft:cpe23","value":"cpe:2.3:a:\\@img\\/sharp_libvips_linuxmusl:\\@img\\/sharp-libvips-linuxmusl-arm64:1.2.4:*:*:*:*:*:*:*"},{"name":"syft:cpe23","value":"cpe:2.3:a:\\@img\\/sharp_libvips_linuxmusl:\\@img\\/sharp_libvips_linuxmusl_arm64:1.2.4:*:*:*:*:*:*:*"},{"name":"syft:cpe23","value":"cpe:2.3:a:\\@img\\/sharp-libvips:\\@img\\/sharp-libvips-linuxmusl-arm64:1.2.4:*:*:*:*:*:*:*"},{"name":"syft:cpe23","value":"cpe:2.3:a:\\@img\\/sharp-libvips:\\@img\\/sharp_libvips_linuxmusl_arm64:1.2.4:*:*:*:*:*:*:*"},{"name":"syft:cpe23","value":"cpe:2.3:a:\\@img\\/sharp_libvips:\\@img\\/sharp-libvips-linuxmusl-arm64:1.2.4:*:*:*:*:*:*:*"},{"name":"syft:cpe23","value":"cpe:2.3:a:\\@img\\/sharp_libvips:\\@img\\/sharp_libvips_linuxmusl_arm64:1.2.4:*:*:*:*:*:*:*"},{"name":"syft:cpe23","value":"cpe:2.3:a:\\@img\\/sharp:\\@img\\/sharp-libvips-linuxmusl-arm64:1.2.4:*:*:*:*:*:*:*"},{"name":"syft:cpe23","value":"cpe:2.3:a:\\@img\\/sharp:\\@img\\/sharp_libvips_linuxmusl_arm64:1.2.4:*:*:*:*:*:*:*"},{"name":"syft:location:0:path","value":"/package-lock.json"}]},{"bom-ref":"pkg:npm/%40img/sharp-libvips-linuxmusl-x64@1.2.4?package-id=ae61d3e41ec21cc4","type":"library","name":"@img/sharp-libvips-linuxmusl-x64","version":"1.2.4","licenses":[{"license":{"id":"LGPL-3.0-or-later"}}],"cpe":"cpe:2.3:a:\\@img\\/sharp-libvips-linuxmusl-x64:\\@img\\/sharp-libvips-linuxmusl-x64:1.2.4:*:*:*:*:*:*:*","purl":"pkg:npm/%40img/sharp-libvips-linuxmusl-x64@1.2.4","properties":[{"name":"syft:package:foundBy","value":"javascript-lock-cataloger"},{"name":"syft:package:language","value":"javascript"},{"name":"syft:package:type","value":"npm"},{"name":"syft:package:metadataType","value":"javascript-npm-package-lock-entry"},{"name":"syft:cpe23","value":"cpe:2.3:a:\\@img\\/sharp-libvips-linuxmusl-x64:\\@img\\/sharp_libvips_linuxmusl_x64:1.2.4:*:*:*:*:*:*:*"},{"name":"syft:cpe23","value":"cpe:2.3:a:\\@img\\/sharp_libvips_linuxmusl_x64:\\@img\\/sharp-libvips-linuxmusl-x64:1.2.4:*:*:*:*:*:*:*"},{"name":"syft:cpe23","value":"cpe:2.3:a:\\@img\\/sharp_libvips_linuxmusl_x64:\\@img\\/sharp_libvips_linuxmusl_x64:1.2.4:*:*:*:*:*:*:*"},{"name":"syft:cpe23","value":"cpe:2.3:a:\\@img\\/sharp-libvips-linuxmusl:\\@img\\/sharp-libvips-linuxmusl-x64:1.2.4:*:*:*:*:*:*:*"},{"name":"syft:cpe23","value":"cpe:2.3:a:\\@img\\/sharp-libvips-linuxmusl:\\@img\\/sharp_libvips_linuxmusl_x64:1.2.4:*:*:*:*:*:*:*"},{"name":"syft:cpe23","value":"cpe:2.3:a:\\@img\\/sharp_libvips_linuxmusl:\\@img\\/sharp-libvips-linuxmusl-x64:1.2.4:*:*:*:*:*:*:*"},{"name":"syft:cpe23","value":"cpe:2.3:a:\\@img\\/sharp_libvips_linuxmusl:\\@img\\/sharp_libvips_linuxmusl_x64:1.2.4:*:*:*:*:*:*:*"},{"name":"syft:cpe23","value":"cpe:2.3:a:\\@img\\/sharp-libvips:\\@img\\/sharp-libvips-linuxmusl-x64:1.2.4:*:*:*:*:*:*:*"},{"name":"syft:cpe23","value":"cpe:2.3:a:\\@img\\/sharp-libvips:\\@img\\/sharp_libvips_linuxmusl_x64:1.2.4:*:*:*:*:*:*:*"},{"name":"syft:cpe23","value":"cpe:2.3:a:\\@img\\/sharp_libvips:\\@img\\/sharp-libvips-linuxmusl-x64:1.2.4:*:*:*:*:*:*:*"},{"name":"syft:cpe23","value":"cpe:2.3:a:\\@img\\/sharp_libvips:\\@img\\/sharp_libvips_linuxmusl_x64:1.2.4:*:*:*:*:*:*:*"},{"name":"syft:cpe23","value":"cpe:2.3:a:\\@img\\/sharp:\\@img\\/sharp-libvips-linuxmusl-x64:1.2.4:*:*:*:*:*:*:*"},{"name":"syft:cpe23","value":"cpe:2.3:a:\\@img\\/sharp:\\@img\\/sharp_libvips_linuxmusl_x64:1.2.4:*:*:*:*:*:*:*"},{"name":"syft:location:0:path","value":"/package-lock.json"}]},{"bom-ref":"pkg:npm/%40img/sharp-linux-arm@0.34.5?package-id=7b0ffe951e8d0184","type":"library","name":"@img/sharp-linux-arm","version":"0.34.5","licenses":[{"license":{"id":"Apache-2.0"}}],"cpe":"cpe:2.3:a:\\@img\\/sharp-linux-arm:\\@img\\/sharp-linux-arm:0.34.5:*:*:*:*:*:*:*","purl":"pkg:npm/%40img/sharp-linux-arm@0.34.5","properties":[{"name":"syft:package:foundBy","value":"javascript-lock-cataloger"},{"name":"syft:package:language","value":"javascript"},{"name":"syft:package:type","value":"npm"},{"name":"syft:package:metadataType","value":"javascript-npm-package-lock-entry"},{"name":"syft:cpe23","value":"cpe:2.3:a:\\@img\\/sharp-linux-arm:\\@img\\/sharp_linux_arm:0.34.5:*:*:*:*:*:*:*"},{"name":"syft:cpe23","value":"cpe:2.3:a:\\@img\\/sharp_linux_arm:\\@img\\/sharp-linux-arm:0.34.5:*:*:*:*:*:*:*"},{"name":"syft:cpe23","value":"cpe:2.3:a:\\@img\\/sharp_linux_arm:\\@img\\/sharp_linux_arm:0.34.5:*:*:*:*:*:*:*"},{"name":"syft:cpe23","value":"cpe:2.3:a:\\@img\\/sharp-linux:\\@img\\/sharp-linux-arm:0.34.5:*:*:*:*:*:*:*"},{"name":"syft:cpe23","value":"cpe:2.3:a:\\@img\\/sharp-linux:\\@img\\/sharp_linux_arm:0.34.5:*:*:*:*:*:*:*"},{"name":"syft:cpe23","value":"cpe:2.3:a:\\@img\\/sharp_linux:\\@img\\/sharp-linux-arm:0.34.5:*:*:*:*:*:*:*"},{"name":"syft:cpe23","value":"cpe:2.3:a:\\@img\\/sharp_linux:\\@img\\/sharp_linux_arm:0.34.5:*:*:*:*:*:*:*"},{"name":"syft:cpe23","value":"cpe:2.3:a:\\@img\\/sharp:\\@img\\/sharp-linux-arm:0.34.5:*:*:*:*:*:*:*"},{"name":"syft:cpe23","value":"cpe:2.3:a:\\@img\\/sharp:\\@img\\/sharp_linux_arm:0.34.5:*:*:*:*:*:*:*"},{"name":"syft:location:0:path","value":"/package-lock.json"}]},{"bom-ref":"pkg:npm/%40img/sharp-linux-arm64@0.34.5?package-id=420460519271eb91","type":"library","name":"@img/sharp-linux-arm64","version":"0.34.5","licenses":[{"license":{"id":"Apache-2.0"}}],"cpe":"cpe:2.3:a:\\@img\\/sharp-linux-arm64:\\@img\\/sharp-linux-arm64:0.34.5:*:*:*:*:*:*:*","purl":"pkg:npm/%40img/sharp-linux-arm64@0.34.5","properties":[{"name":"syft:package:foundBy","value":"javascript-lock-cataloger"},{"name":"syft:package:language","value":"javascript"},{"name":"syft:package:type","value":"npm"},{"name":"syft:package:metadataType","value":"javascript-npm-package-lock-entry"},{"name":"syft:cpe23","value":"cpe:2.3:a:\\@img\\/sharp-linux-arm64:\\@img\\/sharp_linux_arm64:0.34.5:*:*:*:*:*:*:*"},{"name":"syft:cpe23","value":"cpe:2.3:a:\\@img\\/sharp_linux_arm64:\\@img\\/sharp-linux-arm64:0.34.5:*:*:*:*:*:*:*"},{"name":"syft:cpe23","value":"cpe:2.3:a:\\@img\\/sharp_linux_arm64:\\@img\\/sharp_linux_arm64:0.34.5:*:*:*:*:*:*:*"},{"name":"syft:cpe23","value":"cpe:2.3:a:\\@img\\/sharp-linux:\\@img\\/sharp-linux-arm64:0.34.5:*:*:*:*:*:*:*"},{"name":"syft:cpe23","value":"cpe:2.3:a:\\@img\\/sharp-linux:\\@img\\/sharp_linux_arm64:0.34.5:*:*:*:*:*:*:*"},{"name":"syft:cpe23","value":"cpe:2.3:a:\\@img\\/sharp_linux:\\@img\\/sharp-linux-arm64:0.34.5:*:*:*:*:*:*:*"},{"name":"syft:cpe23","value":"cpe:2.3:a:\\@img\\/sharp_linux:\\@img\\/sharp_linux_arm64:0.34.5:*:*:*:*:*:*:*"},{"name":"syft:cpe23","value":"cpe:2.3:a:\\@img\\/sharp:\\@img\\/sharp-linux-arm64:0.34.5:*:*:*:*:*:*:*"},{"name":"syft:cpe23","value":"cpe:2.3:a:\\@img\\/sharp:\\@img\\/sharp_linux_arm64:0.34.5:*:*:*:*:*:*:*"},{"name":"syft:location:0:path","value":"/package-lock.json"}]},{"bom-ref":"pkg:npm/%40img/sharp-linux-ppc64@0.34.5?package-id=1c143f17336dc8ba","type":"library","name":"@img/sharp-linux-ppc64","version":"0.34.5","licenses":[{"license":{"id":"Apache-2.0"}}],"cpe":"cpe:2.3:a:\\@img\\/sharp-linux-ppc64:\\@img\\/sharp-linux-ppc64:0.34.5:*:*:*:*:*:*:*","purl":"pkg:npm/%40img/sharp-linux-ppc64@0.34.5","properties":[{"name":"syft:package:foundBy","value":"javascript-lock-cataloger"},{"name":"syft:package:language","value":"javascript"},{"name":"syft:package:type","value":"npm"},{"name":"syft:package:metadataType","value":"javascript-npm-package-lock-entry"},{"name":"syft:cpe23","value":"cpe:2.3:a:\\@img\\/sharp-linux-ppc64:\\@img\\/sharp_linux_ppc64:0.34.5:*:*:*:*:*:*:*"},{"name":"syft:cpe23","value":"cpe:2.3:a:\\@img\\/sharp_linux_ppc64:\\@img\\/sharp-linux-ppc64:0.34.5:*:*:*:*:*:*:*"},{"name":"syft:cpe23","value":"cpe:2.3:a:\\@img\\/sharp_linux_ppc64:\\@img\\/sharp_linux_ppc64:0.34.5:*:*:*:*:*:*:*"},{"name":"syft:cpe23","value":"cpe:2.3:a:\\@img\\/sharp-linux:\\@img\\/sharp-linux-ppc64:0.34.5:*:*:*:*:*:*:*"},{"name":"syft:cpe23","value":"cpe:2.3:a:\\@img\\/sharp-linux:\\@img\\/sharp_linux_ppc64:0.34.5:*:*:*:*:*:*:*"},{"name":"syft:cpe23","value":"cpe:2.3:a:\\@img\\/sharp_linux:\\@img\\/sharp-linux-ppc64:0.34.5:*:*:*:*:*:*:*"},{"name":"syft:cpe23","value":"cpe:2.3:a:\\@img\\/sharp_linux:\\@img\\/sharp_linux_ppc64:0.34.5:*:*:*:*:*:*:*"},{"name":"syft:cpe23","value":"cpe:2.3:a:\\@img\\/sharp:\\@img\\/sharp-linux-ppc64:0.34.5:*:*:*:*:*:*:*"},{"name":"syft:cpe23","value":"cpe:2.3:a:\\@img\\/sharp:\\@img\\/sharp_linux_ppc64:0.34.5:*:*:*:*:*:*:*"},{"name":"syft:location:0:path","value":"/package-lock.json"}]},{"bom-ref":"pkg:npm/%40img/sharp-linux-riscv64@0.34.5?package-id=3d5f0073301e1dd2","type":"library","name":"@img/sharp-linux-riscv64","version":"0.34.5","licenses":[{"license":{"id":"Apache-2.0"}}],"cpe":"cpe:2.3:a:\\@img\\/sharp-linux-riscv64:\\@img\\/sharp-linux-riscv64:0.34.5:*:*:*:*:*:*:*","purl":"pkg:npm/%40img/sharp-linux-riscv64@0.34.5","properties":[{"name":"syft:package:foundBy","value":"javascript-lock-cataloger"},{"name":"syft:package:language","value":"javascript"},{"name":"syft:package:type","value":"npm"},{"name":"syft:package:metadataType","value":"javascript-npm-package-lock-entry"},{"name":"syft:cpe23","value":"cpe:2.3:a:\\@img\\/sharp-linux-riscv64:\\@img\\/sharp_linux_riscv64:0.34.5:*:*:*:*:*:*:*"},{"name":"syft:cpe23","value":"cpe:2.3:a:\\@img\\/sharp_linux_riscv64:\\@img\\/sharp-linux-riscv64:0.34.5:*:*:*:*:*:*:*"},{"name":"syft:cpe23","value":"cpe:2.3:a:\\@img\\/sharp_linux_riscv64:\\@img\\/sharp_linux_riscv64:0.34.5:*:*:*:*:*:*:*"},{"name":"syft:cpe23","value":"cpe:2.3:a:\\@img\\/sharp-linux:\\@img\\/sharp-linux-riscv64:0.34.5:*:*:*:*:*:*:*"},{"name":"syft:cpe23","value":"cpe:2.3:a:\\@img\\/sharp-linux:\\@img\\/sharp_linux_riscv64:0.34.5:*:*:*:*:*:*:*"},{"name":"syft:cpe23","value":"cpe:2.3:a:\\@img\\/sharp_linux:\\@img\\/sharp-linux-riscv64:0.34.5:*:*:*:*:*:*:*"},{"name":"syft:cpe23","value":"cpe:2.3:a:\\@img\\/sharp_linux:\\@img\\/sharp_linux_riscv64:0.34.5:*:*:*:*:*:*:*"},{"name":"syft:cpe23","value":"cpe:2.3:a:\\@img\\/sharp:\\@img\\/sharp-linux-riscv64:0.34.5:*:*:*:*:*:*:*"},{"name":"syft:cpe23","value":"cpe:2.3:a:\\@img\\/sharp:\\@img\\/sharp_linux_riscv64:0.34.5:*:*:*:*:*:*:*"},{"name":"syft:location:0:path","value":"/package-lock.json"}]},{"bom-ref":"pkg:npm/%40img/sharp-linux-s390x@0.34.5?package-id=c076e6d4d78c34bf","type":"library","name":"@img/sharp-linux-s390x","version":"0.34.5","licenses":[{"license":{"id":"Apache-2.0"}}],"cpe":"cpe:2.3:a:\\@img\\/sharp-linux-s390x:\\@img\\/sharp-linux-s390x:0.34.5:*:*:*:*:*:*:*","purl":"pkg:npm/%40img/sharp-linux-s390x@0.34.5","properties":[{"name":"syft:package:foundBy","value":"javascript-lock-cataloger"},{"name":"syft:package:language","value":"javascript"},{"name":"syft:package:type","value":"npm"},{"name":"syft:package:metadataType","value":"javascript-npm-package-lock-entry"},{"name":"syft:cpe23","value":"cpe:2.3:a:\\@img\\/sharp-linux-s390x:\\@img\\/sharp_linux_s390x:0.34.5:*:*:*:*:*:*:*"},{"name":"syft:cpe23","value":"cpe:2.3:a:\\@img\\/sharp_linux_s390x:\\@img\\/sharp-linux-s390x:0.34.5:*:*:*:*:*:*:*"},{"name":"syft:cpe23","value":"cpe:2.3:a:\\@img\\/sharp_linux_s390x:\\@img\\/sharp_linux_s390x:0.34.5:*:*:*:*:*:*:*"},{"name":"syft:cpe23","value":"cpe:2.3:a:\\@img\\/sharp-linux:\\@img\\/sharp-linux-s390x:0.34.5:*:*:*:*:*:*:*"},{"name":"syft:cpe23","value":"cpe:2.3:a:\\@img\\/sharp-linux:\\@img\\/sharp_linux_s390x:0.34.5:*:*:*:*:*:*:*"},{"name":"syft:cpe23","value":"cpe:2.3:a:\\@img\\/sharp_linux:\\@img\\/sharp-linux-s390x:0.34.5:*:*:*:*:*:*:*"},{"name":"syft:cpe23","value":"cpe:2.3:a:\\@img\\/sharp_linux:\\@img\\/sharp_linux_s390x:0.34.5:*:*:*:*:*:*:*"},{"name":"syft:cpe23","value":"cpe:2.3:a:\\@img\\/sharp:\\@img\\/sharp-linux-s390x:0.34.5:*:*:*:*:*:*:*"},{"name":"syft:cpe23","value":"cpe:2.3:a:\\@img\\/sharp:\\@img\\/sharp_linux_s390x:0.34.5:*:*:*:*:*:*:*"},{"name":"syft:location:0:path","value":"/package-lock.json"}]},{"bom-ref":"pkg:npm/%40img/sharp-linux-x64@0.34.5?package-id=5c34e4aa207741ba","type":"library","name":"@img/sharp-linux-x64","version":"0.34.5","licenses":[{"license":{"id":"Apache-2.0"}}],"cpe":"cpe:2.3:a:\\@img\\/sharp-linux-x64:\\@img\\/sharp-linux-x64:0.34.5:*:*:*:*:*:*:*","purl":"pkg:npm/%40img/sharp-linux-x64@0.34.5","properties":[{"name":"syft:package:foundBy","value":"javascript-lock-cataloger"},{"name":"syft:package:language","value":"javascript"},{"name":"syft:package:type","value":"npm"},{"name":"syft:package:metadataType","value":"javascript-npm-package-lock-entry"},{"name":"syft:cpe23","value":"cpe:2.3:a:\\@img\\/sharp-linux-x64:\\@img\\/sharp_linux_x64:0.34.5:*:*:*:*:*:*:*"},{"name":"syft:cpe23","value":"cpe:2.3:a:\\@img\\/sharp_linux_x64:\\@img\\/sharp-linux-x64:0.34.5:*:*:*:*:*:*:*"},{"name":"syft:cpe23","value":"cpe:2.3:a:\\@img\\/sharp_linux_x64:\\@img\\/sharp_linux_x64:0.34.5:*:*:*:*:*:*:*"},{"name":"syft:cpe23","value":"cpe:2.3:a:\\@img\\/sharp-linux:\\@img\\/sharp-linux-x64:0.34.5:*:*:*:*:*:*:*"},{"name":"syft:cpe23","value":"cpe:2.3:a:\\@img\\/sharp-linux:\\@img\\/sharp_linux_x64:0.34.5:*:*:*:*:*:*:*"},{"name":"syft:cpe23","value":"cpe:2.3:a:\\@img\\/sharp_linux:\\@img\\/sharp-linux-x64:0.34.5:*:*:*:*:*:*:*"},{"name":"syft:cpe23","value":"cpe:2.3:a:\\@img\\/sharp_linux:\\@img\\/sharp_linux_x64:0.34.5:*:*:*:*:*:*:*"},{"name":"syft:cpe23","value":"cpe:2.3:a:\\@img\\/sharp:\\@img\\/sharp-linux-x64:0.34.5:*:*:*:*:*:*:*"},{"name":"syft:cpe23","value":"cpe:2.3:a:\\@img\\/sharp:\\@img\\/sharp_linux_x64:0.34.5:*:*:*:*:*:*:*"},{"name":"syft:location:0:path","value":"/package-lock.json"}]},{"bom-ref":"pkg:npm/%40img/sharp-linuxmusl-arm64@0.34.5?package-id=bd23ea866b52bb05","type":"library","name":"@img/sharp-linuxmusl-arm64","version":"0.34.5","licenses":[{"license":{"id":"Apache-2.0"}}],"cpe":"cpe:2.3:a:\\@img\\/sharp-linuxmusl-arm64:\\@img\\/sharp-linuxmusl-arm64:0.34.5:*:*:*:*:*:*:*","purl":"pkg:npm/%40img/sharp-linuxmusl-arm64@0.34.5","properties":[{"name":"syft:package:foundBy","value":"javascript-lock-cataloger"},{"name":"syft:package:language","value":"javascript"},{"name":"syft:package:type","value":"npm"},{"name":"syft:package:metadataType","value":"javascript-npm-package-lock-entry"},{"name":"syft:cpe23","value":"cpe:2.3:a:\\@img\\/sharp-linuxmusl-arm64:\\@img\\/sharp_linuxmusl_arm64:0.34.5:*:*:*:*:*:*:*"},{"name":"syft:cpe23","value":"cpe:2.3:a:\\@img\\/sharp_linuxmusl_arm64:\\@img\\/sharp-linuxmusl-arm64:0.34.5:*:*:*:*:*:*:*"},{"name":"syft:cpe23","value":"cpe:2.3:a:\\@img\\/sharp_linuxmusl_arm64:\\@img\\/sharp_linuxmusl_arm64:0.34.5:*:*:*:*:*:*:*"},{"name":"syft:cpe23","value":"cpe:2.3:a:\\@img\\/sharp-linuxmusl:\\@img\\/sharp-linuxmusl-arm64:0.34.5:*:*:*:*:*:*:*"},{"name":"syft:cpe23","value":"cpe:2.3:a:\\@img\\/sharp-linuxmusl:\\@img\\/sharp_linuxmusl_arm64:0.34.5:*:*:*:*:*:*:*"},{"name":"syft:cpe23","value":"cpe:2.3:a:\\@img\\/sharp_linuxmusl:\\@img\\/sharp-linuxmusl-arm64:0.34.5:*:*:*:*:*:*:*"},{"name":"syft:cpe23","value":"cpe:2.3:a:\\@img\\/sharp_linuxmusl:\\@img\\/sharp_linuxmusl_arm64:0.34.5:*:*:*:*:*:*:*"},{"name":"syft:cpe23","value":"cpe:2.3:a:\\@img\\/sharp:\\@img\\/sharp-linuxmusl-arm64:0.34.5:*:*:*:*:*:*:*"},{"name":"syft:cpe23","value":"cpe:2.3:a:\\@img\\/sharp:\\@img\\/sharp_linuxmusl_arm64:0.34.5:*:*:*:*:*:*:*"},{"name":"syft:location:0:path","value":"/package-lock.json"}]},{"bom-ref":"pkg:npm/%40img/sharp-linuxmusl-x64@0.34.5?package-id=65992b394e188f69","type":"library","name":"@img/sharp-linuxmusl-x64","version":"0.34.5","licenses":[{"license":{"id":"Apache-2.0"}}],"cpe":"cpe:2.3:a:\\@img\\/sharp-linuxmusl-x64:\\@img\\/sharp-linuxmusl-x64:0.34.5:*:*:*:*:*:*:*","purl":"pkg:npm/%40img/sharp-linuxmusl-x64@0.34.5","properties":[{"name":"syft:package:foundBy","value":"javascript-lock-cataloger"},{"name":"syft:package:language","value":"javascript"},{"name":"syft:package:type","value":"npm"},{"name":"syft:package:metadataType","value":"javascript-npm-package-lock-entry"},{"name":"syft:cpe23","value":"cpe:2.3:a:\\@img\\/sharp-linuxmusl-x64:\\@img\\/sharp_linuxmusl_x64:0.34.5:*:*:*:*:*:*:*"},{"name":"syft:cpe23","value":"cpe:2.3:a:\\@img\\/sharp_linuxmusl_x64:\\@img\\/sharp-linuxmusl-x64:0.34.5:*:*:*:*:*:*:*"},{"name":"syft:cpe23","value":"cpe:2.3:a:\\@img\\/sharp_linuxmusl_x64:\\@img\\/sharp_linuxmusl_x64:0.34.5:*:*:*:*:*:*:*"},{"name":"syft:cpe23","value":"cpe:2.3:a:\\@img\\/sharp-linuxmusl:\\@img\\/sharp-linuxmusl-x64:0.34.5:*:*:*:*:*:*:*"},{"name":"syft:cpe23","value":"cpe:2.3:a:\\@img\\/sharp-linuxmusl:\\@img\\/sharp_linuxmusl_x64:0.34.5:*:*:*:*:*:*:*"},{"name":"syft:cpe23","value":"cpe:2.3:a:\\@img\\/sharp_linuxmusl:\\@img\\/sharp-linuxmusl-x64:0.34.5:*:*:*:*:*:*:*"},{"name":"syft:cpe23","value":"cpe:2.3:a:\\@img\\/sharp_linuxmusl:\\@img\\/sharp_linuxmusl_x64:0.34.5:*:*:*:*:*:*:*"},{"name":"syft:cpe23","value":"cpe:2.3:a:\\@img\\/sharp:\\@img\\/sharp-linuxmusl-x64:0.34.5:*:*:*:*:*:*:*"},{"name":"syft:cpe23","value":"cpe:2.3:a:\\@img\\/sharp:\\@img\\/sharp_linuxmusl_x64:0.34.5:*:*:*:*:*:*:*"},{"name":"syft:location:0:path","value":"/package-lock.json"}]},{"bom-ref":"pkg:npm/%40img/sharp-wasm32@0.34.5?package-id=30176196030afc73","type":"library","name":"@img/sharp-wasm32","version":"0.34.5","licenses":[{"expression":"Apache-2.0 AND LGPL-3.0-or-later AND MIT"}],"cpe":"cpe:2.3:a:\\@img\\/sharp-wasm32:\\@img\\/sharp-wasm32:0.34.5:*:*:*:*:*:*:*","purl":"pkg:npm/%40img/sharp-wasm32@0.34.5","properties":[{"name":"syft:package:foundBy","value":"javascript-lock-cataloger"},{"name":"syft:package:language","value":"javascript"},{"name":"syft:package:type","value":"npm"},{"name":"syft:package:metadataType","value":"javascript-npm-package-lock-entry"},{"name":"syft:cpe23","value":"cpe:2.3:a:\\@img\\/sharp-wasm32:\\@img\\/sharp_wasm32:0.34.5:*:*:*:*:*:*:*"},{"name":"syft:cpe23","value":"cpe:2.3:a:\\@img\\/sharp_wasm32:\\@img\\/sharp-wasm32:0.34.5:*:*:*:*:*:*:*"},{"name":"syft:cpe23","value":"cpe:2.3:a:\\@img\\/sharp_wasm32:\\@img\\/sharp_wasm32:0.34.5:*:*:*:*:*:*:*"},{"name":"syft:cpe23","value":"cpe:2.3:a:\\@img\\/sharp:\\@img\\/sharp-wasm32:0.34.5:*:*:*:*:*:*:*"},{"name":"syft:cpe23","value":"cpe:2.3:a:\\@img\\/sharp:\\@img\\/sharp_wasm32:0.34.5:*:*:*:*:*:*:*"},{"name":"syft:location:0:path","value":"/package-lock.json"}]},{"bom-ref":"pkg:npm/%40img/sharp-win32-arm64@0.34.5?package-id=954dc0ab9f62b8e2","type":"library","name":"@img/sharp-win32-arm64","version":"0.34.5","licenses":[{"expression":"Apache-2.0 AND LGPL-3.0-or-later"}],"cpe":"cpe:2.3:a:\\@img\\/sharp-win32-arm64:\\@img\\/sharp-win32-arm64:0.34.5:*:*:*:*:*:*:*","purl":"pkg:npm/%40img/sharp-win32-arm64@0.34.5","properties":[{"name":"syft:package:foundBy","value":"javascript-lock-cataloger"},{"name":"syft:package:language","value":"javascript"},{"name":"syft:package:type","value":"npm"},{"name":"syft:package:metadataType","value":"javascript-npm-package-lock-entry"},{"name":"syft:cpe23","value":"cpe:2.3:a:\\@img\\/sharp-win32-arm64:\\@img\\/sharp_win32_arm64:0.34.5:*:*:*:*:*:*:*"},{"name":"syft:cpe23","value":"cpe:2.3:a:\\@img\\/sharp_win32_arm64:\\@img\\/sharp-win32-arm64:0.34.5:*:*:*:*:*:*:*"},{"name":"syft:cpe23","value":"cpe:2.3:a:\\@img\\/sharp_win32_arm64:\\@img\\/sharp_win32_arm64:0.34.5:*:*:*:*:*:*:*"},{"name":"syft:cpe23","value":"cpe:2.3:a:\\@img\\/sharp-win32:\\@img\\/sharp-win32-arm64:0.34.5:*:*:*:*:*:*:*"},{"name":"syft:cpe23","value":"cpe:2.3:a:\\@img\\/sharp-win32:\\@img\\/sharp_win32_arm64:0.34.5:*:*:*:*:*:*:*"},{"name":"syft:cpe23","value":"cpe:2.3:a:\\@img\\/sharp_win32:\\@img\\/sharp-win32-arm64:0.34.5:*:*:*:*:*:*:*"},{"name":"syft:cpe23","value":"cpe:2.3:a:\\@img\\/sharp_win32:\\@img\\/sharp_win32_arm64:0.34.5:*:*:*:*:*:*:*"},{"name":"syft:cpe23","value":"cpe:2.3:a:\\@img\\/sharp:\\@img\\/sharp-win32-arm64:0.34.5:*:*:*:*:*:*:*"},{"name":"syft:cpe23","value":"cpe:2.3:a:\\@img\\/sharp:\\@img\\/sharp_win32_arm64:0.34.5:*:*:*:*:*:*:*"},{"name":"syft:location:0:path","value":"/package-lock.json"}]},{"bom-ref":"pkg:npm/%40img/sharp-win32-ia32@0.34.5?package-id=dfc9495f507f1e89","type":"library","name":"@img/sharp-win32-ia32","version":"0.34.5","licenses":[{"expression":"Apache-2.0 AND LGPL-3.0-or-later"}],"cpe":"cpe:2.3:a:\\@img\\/sharp-win32-ia32:\\@img\\/sharp-win32-ia32:0.34.5:*:*:*:*:*:*:*","purl":"pkg:npm/%40img/sharp-win32-ia32@0.34.5","properties":[{"name":"syft:package:foundBy","value":"javascript-lock-cataloger"},{"name":"syft:package:language","value":"javascript"},{"name":"syft:package:type","value":"npm"},{"name":"syft:package:metadataType","value":"javascript-npm-package-lock-entry"},{"name":"syft:cpe23","value":"cpe:2.3:a:\\@img\\/sharp-win32-ia32:\\@img\\/sharp_win32_ia32:0.34.5:*:*:*:*:*:*:*"},{"name":"syft:cpe23","value":"cpe:2.3:a:\\@img\\/sharp_win32_ia32:\\@img\\/sharp-win32-ia32:0.34.5:*:*:*:*:*:*:*"},{"name":"syft:cpe23","value":"cpe:2.3:a:\\@img\\/sharp_win32_ia32:\\@img\\/sharp_win32_ia32:0.34.5:*:*:*:*:*:*:*"},{"name":"syft:cpe23","value":"cpe:2.3:a:\\@img\\/sharp-win32:\\@img\\/sharp-win32-ia32:0.34.5:*:*:*:*:*:*:*"},{"name":"syft:cpe23","value":"cpe:2.3:a:\\@img\\/sharp-win32:\\@img\\/sharp_win32_ia32:0.34.5:*:*:*:*:*:*:*"},{"name":"syft:cpe23","value":"cpe:2.3:a:\\@img\\/sharp_win32:\\@img\\/sharp-win32-ia32:0.34.5:*:*:*:*:*:*:*"},{"name":"syft:cpe23","value":"cpe:2.3:a:\\@img\\/sharp_win32:\\@img\\/sharp_win32_ia32:0.34.5:*:*:*:*:*:*:*"},{"name":"syft:cpe23","value":"cpe:2.3:a:\\@img\\/sharp:\\@img\\/sharp-win32-ia32:0.34.5:*:*:*:*:*:*:*"},{"name":"syft:cpe23","value":"cpe:2.3:a:\\@img\\/sharp:\\@img\\/sharp_win32_ia32:0.34.5:*:*:*:*:*:*:*"},{"name":"syft:location:0:path","value":"/package-lock.json"}]},{"bom-ref":"pkg:npm/%40img/sharp-win32-x64@0.34.5?package-id=1c0a406403881cb8","type":"library","name":"@img/sharp-win32-x64","version":"0.34.5","licenses":[{"expression":"Apache-2.0 AND LGPL-3.0-or-later"}],"cpe":"cpe:2.3:a:\\@img\\/sharp-win32-x64:\\@img\\/sharp-win32-x64:0.34.5:*:*:*:*:*:*:*","purl":"pkg:npm/%40img/sharp-win32-x64@0.34.5","properties":[{"name":"syft:package:foundBy","value":"javascript-lock-cataloger"},{"name":"syft:package:language","value":"javascript"},{"name":"syft:package:type","value":"npm"},{"name":"syft:package:metadataType","value":"javascript-npm-package-lock-entry"},{"name":"syft:cpe23","value":"cpe:2.3:a:\\@img\\/sharp-win32-x64:\\@img\\/sharp_win32_x64:0.34.5:*:*:*:*:*:*:*"},{"name":"syft:cpe23","value":"cpe:2.3:a:\\@img\\/sharp_win32_x64:\\@img\\/sharp-win32-x64:0.34.5:*:*:*:*:*:*:*"},{"name":"syft:cpe23","value":"cpe:2.3:a:\\@img\\/sharp_win32_x64:\\@img\\/sharp_win32_x64:0.34.5:*:*:*:*:*:*:*"},{"name":"syft:cpe23","value":"cpe:2.3:a:\\@img\\/sharp-win32:\\@img\\/sharp-win32-x64:0.34.5:*:*:*:*:*:*:*"},{"name":"syft:cpe23","value":"cpe:2.3:a:\\@img\\/sharp-win32:\\@img\\/sharp_win32_x64:0.34.5:*:*:*:*:*:*:*"},{"name":"syft:cpe23","value":"cpe:2.3:a:\\@img\\/sharp_win32:\\@img\\/sharp-win32-x64:0.34.5:*:*:*:*:*:*:*"},{"name":"syft:cpe23","value":"cpe:2.3:a:\\@img\\/sharp_win32:\\@img\\/sharp_win32_x64:0.34.5:*:*:*:*:*:*:*"},{"name":"syft:cpe23","value":"cpe:2.3:a:\\@img\\/sharp:\\@img\\/sharp-win32-x64:0.34.5:*:*:*:*:*:*:*"},{"name":"syft:cpe23","value":"cpe:2.3:a:\\@img\\/sharp:\\@img\\/sharp_win32_x64:0.34.5:*:*:*:*:*:*:*"},{"name":"syft:location:0:path","value":"/package-lock.json"}]},{"bom-ref":"pkg:npm/%40next/env@16.0.1?package-id=c2f55e264dc92d3b","type":"library","name":"@next/env","version":"16.0.1","licenses":[{"license":{"id":"MIT"}}],"cpe":"cpe:2.3:a:\\@next\\/env:\\@next\\/env:16.0.1:*:*:*:*:*:*:*","purl":"pkg:npm/%40next/env@16.0.1","properties":[{"name":"syft:package:foundBy","value":"javascript-lock-cataloger"},{"name":"syft:package:language","value":"javascript"},{"name":"syft:package:type","value":"npm"},{"name":"syft:package:metadataType","value":"javascript-npm-package-lock-entry"},{"name":"syft:location:0:path","value":"/package-lock.json"}]},{"bom-ref":"pkg:npm/%40next/swc-darwin-arm64@16.0.1?package-id=1663b10569cf8c04","type":"library","name":"@next/swc-darwin-arm64","version":"16.0.1","licenses":[{"license":{"id":"MIT"}}],"cpe":"cpe:2.3:a:\\@next\\/swc-darwin-arm64:\\@next\\/swc-darwin-arm64:16.0.1:*:*:*:*:*:*:*","purl":"pkg:npm/%40next/swc-darwin-arm64@16.0.1","properties":[{"name":"syft:package:foundBy","value":"javascript-lock-cataloger"},{"name":"syft:package:language","value":"javascript"},{"name":"syft:package:type","value":"npm"},{"name":"syft:package:metadataType","value":"javascript-npm-package-lock-entry"},{"name":"syft:cpe23","value":"cpe:2.3:a:\\@next\\/swc-darwin-arm64:\\@next\\/swc_darwin_arm64:16.0.1:*:*:*:*:*:*:*"},{"name":"syft:cpe23","value":"cpe:2.3:a:\\@next\\/swc_darwin_arm64:\\@next\\/swc-darwin-arm64:16.0.1:*:*:*:*:*:*:*"},{"name":"syft:cpe23","value":"cpe:2.3:a:\\@next\\/swc_darwin_arm64:\\@next\\/swc_darwin_arm64:16.0.1:*:*:*:*:*:*:*"},{"name":"syft:cpe23","value":"cpe:2.3:a:\\@next\\/swc-darwin:\\@next\\/swc-darwin-arm64:16.0.1:*:*:*:*:*:*:*"},{"name":"syft:cpe23","value":"cpe:2.3:a:\\@next\\/swc-darwin:\\@next\\/swc_darwin_arm64:16.0.1:*:*:*:*:*:*:*"},{"name":"syft:cpe23","value":"cpe:2.3:a:\\@next\\/swc_darwin:\\@next\\/swc-darwin-arm64:16.0.1:*:*:*:*:*:*:*"},{"name":"syft:cpe23","value":"cpe:2.3:a:\\@next\\/swc_darwin:\\@next\\/swc_darwin_arm64:16.0.1:*:*:*:*:*:*:*"},{"name":"syft:cpe23","value":"cpe:2.3:a:\\@next\\/swc:\\@next\\/swc-darwin-arm64:16.0.1:*:*:*:*:*:*:*"},{"name":"syft:cpe23","value":"cpe:2.3:a:\\@next\\/swc:\\@next\\/swc_darwin_arm64:16.0.1:*:*:*:*:*:*:*"},{"name":"syft:location:0:path","value":"/package-lock.json"}]},{"bom-ref":"pkg:npm/%40next/swc-darwin-x64@16.0.1?package-id=c5d05e0ce9348180","type":"library","name":"@next/swc-darwin-x64","version":"16.0.1","licenses":[{"license":{"id":"MIT"}}],"cpe":"cpe:2.3:a:\\@next\\/swc-darwin-x64:\\@next\\/swc-darwin-x64:16.0.1:*:*:*:*:*:*:*","purl":"pkg:npm/%40next/swc-darwin-x64@16.0.1","properties":[{"name":"syft:package:foundBy","value":"javascript-lock-cataloger"},{"name":"syft:package:language","value":"javascript"},{"name":"syft:package:type","value":"npm"},{"name":"syft:package:metadataType","value":"javascript-npm-package-lock-entry"},{"name":"syft:cpe23","value":"cpe:2.3:a:\\@next\\/swc-darwin-x64:\\@next\\/swc_darwin_x64:16.0.1:*:*:*:*:*:*:*"},{"name":"syft:cpe23","value":"cpe:2.3:a:\\@next\\/swc_darwin_x64:\\@next\\/swc-darwin-x64:16.0.1:*:*:*:*:*:*:*"},{"name":"syft:cpe23","value":"cpe:2.3:a:\\@next\\/swc_darwin_x64:\\@next\\/swc_darwin_x64:16.0.1:*:*:*:*:*:*:*"},{"name":"syft:cpe23","value":"cpe:2.3:a:\\@next\\/swc-darwin:\\@next\\/swc-darwin-x64:16.0.1:*:*:*:*:*:*:*"},{"name":"syft:cpe23","value":"cpe:2.3:a:\\@next\\/swc-darwin:\\@next\\/swc_darwin_x64:16.0.1:*:*:*:*:*:*:*"},{"name":"syft:cpe23","value":"cpe:2.3:a:\\@next\\/swc_darwin:\\@next\\/swc-darwin-x64:16.0.1:*:*:*:*:*:*:*"},{"name":"syft:cpe23","value":"cpe:2.3:a:\\@next\\/swc_darwin:\\@next\\/swc_darwin_x64:16.0.1:*:*:*:*:*:*:*"},{"name":"syft:cpe23","value":"cpe:2.3:a:\\@next\\/swc:\\@next\\/swc-darwin-x64:16.0.1:*:*:*:*:*:*:*"},{"name":"syft:cpe23","value":"cpe:2.3:a:\\@next\\/swc:\\@next\\/swc_darwin_x64:16.0.1:*:*:*:*:*:*:*"},{"name":"syft:location:0:path","value":"/package-lock.json"}]},{"bom-ref":"pkg:npm/%40next/swc-linux-arm64-gnu@16.0.1?package-id=c708f6d08252b949","type":"library","name":"@next/swc-linux-arm64-gnu","version":"16.0.1","licenses":[{"license":{"id":"MIT"}}],"cpe":"cpe:2.3:a:\\@next\\/swc-linux-arm64-gnu:\\@next\\/swc-linux-arm64-gnu:16.0.1:*:*:*:*:*:*:*","purl":"pkg:npm/%40next/swc-linux-arm64-gnu@16.0.1","properties":[{"name":"syft:package:foundBy","value":"javascript-lock-cataloger"},{"name":"syft:package:language","value":"javascript"},{"name":"syft:package:type","value":"npm"},{"name":"syft:package:metadataType","value":"javascript-npm-package-lock-entry"},{"name":"syft:cpe23","value":"cpe:2.3:a:\\@next\\/swc-linux-arm64-gnu:\\@next\\/swc_linux_arm64_gnu:16.0.1:*:*:*:*:*:*:*"},{"name":"syft:cpe23","value":"cpe:2.3:a:\\@next\\/swc_linux_arm64_gnu:\\@next\\/swc-linux-arm64-gnu:16.0.1:*:*:*:*:*:*:*"},{"name":"syft:cpe23","value":"cpe:2.3:a:\\@next\\/swc_linux_arm64_gnu:\\@next\\/swc_linux_arm64_gnu:16.0.1:*:*:*:*:*:*:*"},{"name":"syft:cpe23","value":"cpe:2.3:a:\\@next\\/swc-linux-arm64:\\@next\\/swc-linux-arm64-gnu:16.0.1:*:*:*:*:*:*:*"},{"name":"syft:cpe23","value":"cpe:2.3:a:\\@next\\/swc-linux-arm64:\\@next\\/swc_linux_arm64_gnu:16.0.1:*:*:*:*:*:*:*"},{"name":"syft:cpe23","value":"cpe:2.3:a:\\@next\\/swc_linux_arm64:\\@next\\/swc-linux-arm64-gnu:16.0.1:*:*:*:*:*:*:*"},{"name":"syft:cpe23","value":"cpe:2.3:a:\\@next\\/swc_linux_arm64:\\@next\\/swc_linux_arm64_gnu:16.0.1:*:*:*:*:*:*:*"},{"name":"syft:cpe23","value":"cpe:2.3:a:\\@next\\/swc-linux:\\@next\\/swc-linux-arm64-gnu:16.0.1:*:*:*:*:*:*:*"},{"name":"syft:cpe23","value":"cpe:2.3:a:\\@next\\/swc-linux:\\@next\\/swc_linux_arm64_gnu:16.0.1:*:*:*:*:*:*:*"},{"name":"syft:cpe23","value":"cpe:2.3:a:\\@next\\/swc_linux:\\@next\\/swc-linux-arm64-gnu:16.0.1:*:*:*:*:*:*:*"},{"name":"syft:cpe23","value":"cpe:2.3:a:\\@next\\/swc_linux:\\@next\\/swc_linux_arm64_gnu:16.0.1:*:*:*:*:*:*:*"},{"name":"syft:cpe23","value":"cpe:2.3:a:\\@next\\/swc:\\@next\\/swc-linux-arm64-gnu:16.0.1:*:*:*:*:*:*:*"},{"name":"syft:cpe23","value":"cpe:2.3:a:\\@next\\/swc:\\@next\\/swc_linux_arm64_gnu:16.0.1:*:*:*:*:*:*:*"},{"name":"syft:location:0:path","value":"/package-lock.json"}]},{"bom-ref":"pkg:npm/%40next/swc-linux-arm64-musl@16.0.1?package-id=378ff112317c70a6","type":"library","name":"@next/swc-linux-arm64-musl","version":"16.0.1","licenses":[{"license":{"id":"MIT"}}],"cpe":"cpe:2.3:a:\\@next\\/swc-linux-arm64-musl:\\@next\\/swc-linux-arm64-musl:16.0.1:*:*:*:*:*:*:*","purl":"pkg:npm/%40next/swc-linux-arm64-musl@16.0.1","properties":[{"name":"syft:package:foundBy","value":"javascript-lock-cataloger"},{"name":"syft:package:language","value":"javascript"},{"name":"syft:package:type","value":"npm"},{"name":"syft:package:metadataType","value":"javascript-npm-package-lock-entry"},{"name":"syft:cpe23","value":"cpe:2.3:a:\\@next\\/swc-linux-arm64-musl:\\@next\\/swc_linux_arm64_musl:16.0.1:*:*:*:*:*:*:*"},{"name":"syft:cpe23","value":"cpe:2.3:a:\\@next\\/swc_linux_arm64_musl:\\@next\\/swc-linux-arm64-musl:16.0.1:*:*:*:*:*:*:*"},{"name":"syft:cpe23","value":"cpe:2.3:a:\\@next\\/swc_linux_arm64_musl:\\@next\\/swc_linux_arm64_musl:16.0.1:*:*:*:*:*:*:*"},{"name":"syft:cpe23","value":"cpe:2.3:a:\\@next\\/swc-linux-arm64:\\@next\\/swc-linux-arm64-musl:16.0.1:*:*:*:*:*:*:*"},{"name":"syft:cpe23","value":"cpe:2.3:a:\\@next\\/swc-linux-arm64:\\@next\\/swc_linux_arm64_musl:16.0.1:*:*:*:*:*:*:*"},{"name":"syft:cpe23","value":"cpe:2.3:a:\\@next\\/swc_linux_arm64:\\@next\\/swc-linux-arm64-musl:16.0.1:*:*:*:*:*:*:*"},{"name":"syft:cpe23","value":"cpe:2.3:a:\\@next\\/swc_linux_arm64:\\@next\\/swc_linux_arm64_musl:16.0.1:*:*:*:*:*:*:*"},{"name":"syft:cpe23","value":"cpe:2.3:a:\\@next\\/swc-linux:\\@next\\/swc-linux-arm64-musl:16.0.1:*:*:*:*:*:*:*"},{"name":"syft:cpe23","value":"cpe:2.3:a:\\@next\\/swc-linux:\\@next\\/swc_linux_arm64_musl:16.0.1:*:*:*:*:*:*:*"},{"name":"syft:cpe23","value":"cpe:2.3:a:\\@next\\/swc_linux:\\@next\\/swc-linux-arm64-musl:16.0.1:*:*:*:*:*:*:*"},{"name":"syft:cpe23","value":"cpe:2.3:a:\\@next\\/swc_linux:\\@next\\/swc_linux_arm64_musl:16.0.1:*:*:*:*:*:*:*"},{"name":"syft:cpe23","value":"cpe:2.3:a:\\@next\\/swc:\\@next\\/swc-linux-arm64-musl:16.0.1:*:*:*:*:*:*:*"},{"name":"syft:cpe23","value":"cpe:2.3:a:\\@next\\/swc:\\@next\\/swc_linux_arm64_musl:16.0.1:*:*:*:*:*:*:*"},{"name":"syft:location:0:path","value":"/package-lock.json"}]},{"bom-ref":"pkg:npm/%40next/swc-linux-x64-gnu@16.0.1?package-id=464e26cfa5ccff65","type":"library","name":"@next/swc-linux-x64-gnu","version":"16.0.1","licenses":[{"license":{"id":"MIT"}}],"cpe":"cpe:2.3:a:\\@next\\/swc-linux-x64-gnu:\\@next\\/swc-linux-x64-gnu:16.0.1:*:*:*:*:*:*:*","purl":"pkg:npm/%40next/swc-linux-x64-gnu@16.0.1","properties":[{"name":"syft:package:foundBy","value":"javascript-lock-cataloger"},{"name":"syft:package:language","value":"javascript"},{"name":"syft:package:type","value":"npm"},{"name":"syft:package:metadataType","value":"javascript-npm-package-lock-entry"},{"name":"syft:cpe23","value":"cpe:2.3:a:\\@next\\/swc-linux-x64-gnu:\\@next\\/swc_linux_x64_gnu:16.0.1:*:*:*:*:*:*:*"},{"name":"syft:cpe23","value":"cpe:2.3:a:\\@next\\/swc_linux_x64_gnu:\\@next\\/swc-linux-x64-gnu:16.0.1:*:*:*:*:*:*:*"},{"name":"syft:cpe23","value":"cpe:2.3:a:\\@next\\/swc_linux_x64_gnu:\\@next\\/swc_linux_x64_gnu:16.0.1:*:*:*:*:*:*:*"},{"name":"syft:cpe23","value":"cpe:2.3:a:\\@next\\/swc-linux-x64:\\@next\\/swc-linux-x64-gnu:16.0.1:*:*:*:*:*:*:*"},{"name":"syft:cpe23","value":"cpe:2.3:a:\\@next\\/swc-linux-x64:\\@next\\/swc_linux_x64_gnu:16.0.1:*:*:*:*:*:*:*"},{"name":"syft:cpe23","value":"cpe:2.3:a:\\@next\\/swc_linux_x64:\\@next\\/swc-linux-x64-gnu:16.0.1:*:*:*:*:*:*:*"},{"name":"syft:cpe23","value":"cpe:2.3:a:\\@next\\/swc_linux_x64:\\@next\\/swc_linux_x64_gnu:16.0.1:*:*:*:*:*:*:*"},{"name":"syft:cpe23","value":"cpe:2.3:a:\\@next\\/swc-linux:\\@next\\/swc-linux-x64-gnu:16.0.1:*:*:*:*:*:*:*"},{"name":"syft:cpe23","value":"cpe:2.3:a:\\@next\\/swc-linux:\\@next\\/swc_linux_x64_gnu:16.0.1:*:*:*:*:*:*:*"},{"name":"syft:cpe23","value":"cpe:2.3:a:\\@next\\/swc_linux:\\@next\\/swc-linux-x64-gnu:16.0.1:*:*:*:*:*:*:*"},{"name":"syft:cpe23","value":"cpe:2.3:a:\\@next\\/swc_linux:\\@next\\/swc_linux_x64_gnu:16.0.1:*:*:*:*:*:*:*"},{"name":"syft:cpe23","value":"cpe:2.3:a:\\@next\\/swc:\\@next\\/swc-linux-x64-gnu:16.0.1:*:*:*:*:*:*:*"},{"name":"syft:cpe23","value":"cpe:2.3:a:\\@next\\/swc:\\@next\\/swc_linux_x64_gnu:16.0.1:*:*:*:*:*:*:*"},{"name":"syft:location:0:path","value":"/package-lock.json"}]},{"bom-ref":"pkg:npm/%40next/swc-linux-x64-musl@16.0.1?package-id=3c15a3b208df25c0","type":"library","name":"@next/swc-linux-x64-musl","version":"16.0.1","licenses":[{"license":{"id":"MIT"}}],"cpe":"cpe:2.3:a:\\@next\\/swc-linux-x64-musl:\\@next\\/swc-linux-x64-musl:16.0.1:*:*:*:*:*:*:*","purl":"pkg:npm/%40next/swc-linux-x64-musl@16.0.1","properties":[{"name":"syft:package:foundBy","value":"javascript-lock-cataloger"},{"name":"syft:package:language","value":"javascript"},{"name":"syft:package:type","value":"npm"},{"name":"syft:package:metadataType","value":"javascript-npm-package-lock-entry"},{"name":"syft:cpe23","value":"cpe:2.3:a:\\@next\\/swc-linux-x64-musl:\\@next\\/swc_linux_x64_musl:16.0.1:*:*:*:*:*:*:*"},{"name":"syft:cpe23","value":"cpe:2.3:a:\\@next\\/swc_linux_x64_musl:\\@next\\/swc-linux-x64-musl:16.0.1:*:*:*:*:*:*:*"},{"name":"syft:cpe23","value":"cpe:2.3:a:\\@next\\/swc_linux_x64_musl:\\@next\\/swc_linux_x64_musl:16.0.1:*:*:*:*:*:*:*"},{"name":"syft:cpe23","value":"cpe:2.3:a:\\@next\\/swc-linux-x64:\\@next\\/swc-linux-x64-musl:16.0.1:*:*:*:*:*:*:*"},{"name":"syft:cpe23","value":"cpe:2.3:a:\\@next\\/swc-linux-x64:\\@next\\/swc_linux_x64_musl:16.0.1:*:*:*:*:*:*:*"},{"name":"syft:cpe23","value":"cpe:2.3:a:\\@next\\/swc_linux_x64:\\@next\\/swc-linux-x64-musl:16.0.1:*:*:*:*:*:*:*"},{"name":"syft:cpe23","value":"cpe:2.3:a:\\@next\\/swc_linux_x64:\\@next\\/swc_linux_x64_musl:16.0.1:*:*:*:*:*:*:*"},{"name":"syft:cpe23","value":"cpe:2.3:a:\\@next\\/swc-linux:\\@next\\/swc-linux-x64-musl:16.0.1:*:*:*:*:*:*:*"},{"name":"syft:cpe23","value":"cpe:2.3:a:\\@next\\/swc-linux:\\@next\\/swc_linux_x64_musl:16.0.1:*:*:*:*:*:*:*"},{"name":"syft:cpe23","value":"cpe:2.3:a:\\@next\\/swc_linux:\\@next\\/swc-linux-x64-musl:16.0.1:*:*:*:*:*:*:*"},{"name":"syft:cpe23","value":"cpe:2.3:a:\\@next\\/swc_linux:\\@next\\/swc_linux_x64_musl:16.0.1:*:*:*:*:*:*:*"},{"name":"syft:cpe23","value":"cpe:2.3:a:\\@next\\/swc:\\@next\\/swc-linux-x64-musl:16.0.1:*:*:*:*:*:*:*"},{"name":"syft:cpe23","value":"cpe:2.3:a:\\@next\\/swc:\\@next\\/swc_linux_x64_musl:16.0.1:*:*:*:*:*:*:*"},{"name":"syft:location:0:path","value":"/package-lock.json"}]},{"bom-ref":"pkg:npm/%40next/swc-win32-arm64-msvc@16.0.1?package-id=85298f9a1bf63d7c","type":"library","name":"@next/swc-win32-arm64-msvc","version":"16.0.1","licenses":[{"license":{"id":"MIT"}}],"cpe":"cpe:2.3:a:\\@next\\/swc-win32-arm64-msvc:\\@next\\/swc-win32-arm64-msvc:16.0.1:*:*:*:*:*:*:*","purl":"pkg:npm/%40next/swc-win32-arm64-msvc@16.0.1","properties":[{"name":"syft:package:foundBy","value":"javascript-lock-cataloger"},{"name":"syft:package:language","value":"javascript"},{"name":"syft:package:type","value":"npm"},{"name":"syft:package:metadataType","value":"javascript-npm-package-lock-entry"},{"name":"syft:cpe23","value":"cpe:2.3:a:\\@next\\/swc-win32-arm64-msvc:\\@next\\/swc_win32_arm64_msvc:16.0.1:*:*:*:*:*:*:*"},{"name":"syft:cpe23","value":"cpe:2.3:a:\\@next\\/swc_win32_arm64_msvc:\\@next\\/swc-win32-arm64-msvc:16.0.1:*:*:*:*:*:*:*"},{"name":"syft:cpe23","value":"cpe:2.3:a:\\@next\\/swc_win32_arm64_msvc:\\@next\\/swc_win32_arm64_msvc:16.0.1:*:*:*:*:*:*:*"},{"name":"syft:cpe23","value":"cpe:2.3:a:\\@next\\/swc-win32-arm64:\\@next\\/swc-win32-arm64-msvc:16.0.1:*:*:*:*:*:*:*"},{"name":"syft:cpe23","value":"cpe:2.3:a:\\@next\\/swc-win32-arm64:\\@next\\/swc_win32_arm64_msvc:16.0.1:*:*:*:*:*:*:*"},{"name":"syft:cpe23","value":"cpe:2.3:a:\\@next\\/swc_win32_arm64:\\@next\\/swc-win32-arm64-msvc:16.0.1:*:*:*:*:*:*:*"},{"name":"syft:cpe23","value":"cpe:2.3:a:\\@next\\/swc_win32_arm64:\\@next\\/swc_win32_arm64_msvc:16.0.1:*:*:*:*:*:*:*"},{"name":"syft:cpe23","value":"cpe:2.3:a:\\@next\\/swc-win32:\\@next\\/swc-win32-arm64-msvc:16.0.1:*:*:*:*:*:*:*"},{"name":"syft:cpe23","value":"cpe:2.3:a:\\@next\\/swc-win32:\\@next\\/swc_win32_arm64_msvc:16.0.1:*:*:*:*:*:*:*"},{"name":"syft:cpe23","value":"cpe:2.3:a:\\@next\\/swc_win32:\\@next\\/swc-win32-arm64-msvc:16.0.1:*:*:*:*:*:*:*"},{"name":"syft:cpe23","value":"cpe:2.3:a:\\@next\\/swc_win32:\\@next\\/swc_win32_arm64_msvc:16.0.1:*:*:*:*:*:*:*"},{"name":"syft:cpe23","value":"cpe:2.3:a:\\@next\\/swc:\\@next\\/swc-win32-arm64-msvc:16.0.1:*:*:*:*:*:*:*"},{"name":"syft:cpe23","value":"cpe:2.3:a:\\@next\\/swc:\\@next\\/swc_win32_arm64_msvc:16.0.1:*:*:*:*:*:*:*"},{"name":"syft:location:0:path","value":"/package-lock.json"}]},{"bom-ref":"pkg:npm/%40next/swc-win32-x64-msvc@16.0.1?package-id=8974b8c140b84029","type":"library","name":"@next/swc-win32-x64-msvc","version":"16.0.1","licenses":[{"license":{"id":"MIT"}}],"cpe":"cpe:2.3:a:\\@next\\/swc-win32-x64-msvc:\\@next\\/swc-win32-x64-msvc:16.0.1:*:*:*:*:*:*:*","purl":"pkg:npm/%40next/swc-win32-x64-msvc@16.0.1","properties":[{"name":"syft:package:foundBy","value":"javascript-lock-cataloger"},{"name":"syft:package:language","value":"javascript"},{"name":"syft:package:type","value":"npm"},{"name":"syft:package:metadataType","value":"javascript-npm-package-lock-entry"},{"name":"syft:cpe23","value":"cpe:2.3:a:\\@next\\/swc-win32-x64-msvc:\\@next\\/swc_win32_x64_msvc:16.0.1:*:*:*:*:*:*:*"},{"name":"syft:cpe23","value":"cpe:2.3:a:\\@next\\/swc_win32_x64_msvc:\\@next\\/swc-win32-x64-msvc:16.0.1:*:*:*:*:*:*:*"},{"name":"syft:cpe23","value":"cpe:2.3:a:\\@next\\/swc_win32_x64_msvc:\\@next\\/swc_win32_x64_msvc:16.0.1:*:*:*:*:*:*:*"},{"name":"syft:cpe23","value":"cpe:2.3:a:\\@next\\/swc-win32-x64:\\@next\\/swc-win32-x64-msvc:16.0.1:*:*:*:*:*:*:*"},{"name":"syft:cpe23","value":"cpe:2.3:a:\\@next\\/swc-win32-x64:\\@next\\/swc_win32_x64_msvc:16.0.1:*:*:*:*:*:*:*"},{"name":"syft:cpe23","value":"cpe:2.3:a:\\@next\\/swc_win32_x64:\\@next\\/swc-win32-x64-msvc:16.0.1:*:*:*:*:*:*:*"},{"name":"syft:cpe23","value":"cpe:2.3:a:\\@next\\/swc_win32_x64:\\@next\\/swc_win32_x64_msvc:16.0.1:*:*:*:*:*:*:*"},{"name":"syft:cpe23","value":"cpe:2.3:a:\\@next\\/swc-win32:\\@next\\/swc-win32-x64-msvc:16.0.1:*:*:*:*:*:*:*"},{"name":"syft:cpe23","value":"cpe:2.3:a:\\@next\\/swc-win32:\\@next\\/swc_win32_x64_msvc:16.0.1:*:*:*:*:*:*:*"},{"name":"syft:cpe23","value":"cpe:2.3:a:\\@next\\/swc_win32:\\@next\\/swc-win32-x64-msvc:16.0.1:*:*:*:*:*:*:*"},{"name":"syft:cpe23","value":"cpe:2.3:a:\\@next\\/swc_win32:\\@next\\/swc_win32_x64_msvc:16.0.1:*:*:*:*:*:*:*"},{"name":"syft:cpe23","value":"cpe:2.3:a:\\@next\\/swc:\\@next\\/swc-win32-x64-msvc:16.0.1:*:*:*:*:*:*:*"},{"name":"syft:cpe23","value":"cpe:2.3:a:\\@next\\/swc:\\@next\\/swc_win32_x64_msvc:16.0.1:*:*:*:*:*:*:*"},{"name":"syft:location:0:path","value":"/package-lock.json"}]},{"bom-ref":"pkg:npm/%40playwright/test@1.56.1?package-id=679266b728f4e6ff","type":"library","name":"@playwright/test","version":"1.56.1","licenses":[{"license":{"id":"Apache-2.0"}}],"cpe":"cpe:2.3:a:\\@playwright\\/test:\\@playwright\\/test:1.56.1:*:*:*:*:*:*:*","purl":"pkg:npm/%40playwright/test@1.56.1","properties":[{"name":"syft:package:foundBy","value":"javascript-lock-cataloger"},{"name":"syft:package:language","value":"javascript"},{"name":"syft:package:type","value":"npm"},{"name":"syft:package:metadataType","value":"javascript-npm-package-lock-entry"},{"name":"syft:location:0:path","value":"/package-lock.json"}]},{"bom-ref":"pkg:npm/%40swc/helpers@0.5.15?package-id=181c5778f3ad4ad9","type":"library","name":"@swc/helpers","version":"0.5.15","licenses":[{"license":{"id":"Apache-2.0"}}],"cpe":"cpe:2.3:a:\\@swc\\/helpers:\\@swc\\/helpers:0.5.15:*:*:*:*:*:*:*","purl":"pkg:npm/%40swc/helpers@0.5.15","properties":[{"name":"syft:package:foundBy","value":"javascript-lock-cataloger"},{"name":"syft:package:language","value":"javascript"},{"name":"syft:package:type","value":"npm"},{"name":"syft:package:metadataType","value":"javascript-npm-package-lock-entry"},{"name":"syft:location:0:path","value":"/package-lock.json"}]},{"bom-ref":"pkg:github/actions/checkout@v3?package-id=da3a65b9745222ee","type":"library","name":"actions/checkout","version":"v3","cpe":"cpe:2.3:a:actions\\/checkout:actions\\/checkout:v3:*:*:*:*:*:*:*","purl":"pkg:github/actions/checkout@v3","properties":[{"name":"syft:package:foundBy","value":"github-actions-usage-cataloger"},{"name":"syft:package:type","value":"github-action"},{"name":"syft:package:metadataType","value":"github-actions-use-statement"},{"name":"syft:location:0:path","value":"/node_modules/fastq/.github/workflows/ci.yml"}]},{"bom-ref":"pkg:github/actions/checkout@v4?package-id=fd10fce47017fa13","type":"library","name":"actions/checkout","version":"v4","cpe":"cpe:2.3:a:actions\\/checkout:actions\\/checkout:v4:*:*:*:*:*:*:*","purl":"pkg:github/actions/checkout@v4","properties":[{"name":"syft:package:foundBy","value":"github-actions-usage-cataloger"},{"name":"syft:package:type","value":"github-action"},{"name":"syft:package:metadataType","value":"github-actions-use-statement"},{"name":"syft:location:0:path","value":"/node_modules/reusify/.github/workflows/ci.yml"}]},{"bom-ref":"pkg:github/actions/checkout@v4?package-id=d46a6577740e5a25","type":"library","name":"actions/checkout","version":"v4","cpe":"cpe:2.3:a:actions\\/checkout:actions\\/checkout:v4:*:*:*:*:*:*:*","purl":"pkg:github/actions/checkout@v4","properties":[{"name":"syft:package:foundBy","value":"github-actions-usage-cataloger"},{"name":"syft:package:type","value":"github-action"},{"name":"syft:package:metadataType","value":"github-actions-use-statement"},{"name":"syft:location:0:path","value":"/node_modules/string.prototype.includes/.github/workflows/publish-on-tag.yml"}]},{"bom-ref":"pkg:github/actions/setup-node@v1?package-id=3c88b1bf4599e259","type":"library","name":"actions/setup-node","version":"v1","cpe":"cpe:2.3:a:actions\\/setup-node:actions\\/setup-node:v1:*:*:*:*:*:*:*","purl":"pkg:github/actions/setup-node@v1","properties":[{"name":"syft:package:foundBy","value":"github-actions-usage-cataloger"},{"name":"syft:package:type","value":"github-action"},{"name":"syft:package:metadataType","value":"github-actions-use-statement"},{"name":"syft:cpe23","value":"cpe:2.3:a:actions\\/setup-node:actions\\/setup_node:v1:*:*:*:*:*:*:*"},{"name":"syft:cpe23","value":"cpe:2.3:a:actions\\/setup_node:actions\\/setup-node:v1:*:*:*:*:*:*:*"},{"name":"syft:cpe23","value":"cpe:2.3:a:actions\\/setup_node:actions\\/setup_node:v1:*:*:*:*:*:*:*"},{"name":"syft:cpe23","value":"cpe:2.3:a:actions\\/setup:actions\\/setup-node:v1:*:*:*:*:*:*:*"},{"name":"syft:cpe23","value":"cpe:2.3:a:actions\\/setup:actions\\/setup_node:v1:*:*:*:*:*:*:*"},{"name":"syft:location:0:path","value":"/node_modules/fastq/.github/workflows/ci.yml"}]},{"bom-ref":"pkg:github/actions/setup-node@v3?package-id=ba0db63f1ea1d49c","type":"library","name":"actions/setup-node","version":"v3","cpe":"cpe:2.3:a:actions\\/setup-node:actions\\/setup-node:v3:*:*:*:*:*:*:*","purl":"pkg:github/actions/setup-node@v3","properties":[{"name":"syft:package:foundBy","value":"github-actions-usage-cataloger"},{"name":"syft:package:type","value":"github-action"},{"name":"syft:package:metadataType","value":"github-actions-use-statement"},{"name":"syft:cpe23","value":"cpe:2.3:a:actions\\/setup-node:actions\\/setup_node:v3:*:*:*:*:*:*:*"},{"name":"syft:cpe23","value":"cpe:2.3:a:actions\\/setup_node:actions\\/setup-node:v3:*:*:*:*:*:*:*"},{"name":"syft:cpe23","value":"cpe:2.3:a:actions\\/setup_node:actions\\/setup_node:v3:*:*:*:*:*:*:*"},{"name":"syft:cpe23","value":"cpe:2.3:a:actions\\/setup:actions\\/setup-node:v3:*:*:*:*:*:*:*"},{"name":"syft:cpe23","value":"cpe:2.3:a:actions\\/setup:actions\\/setup_node:v3:*:*:*:*:*:*:*"},{"name":"syft:location:0:path","value":"/node_modules/fastq/.github/workflows/ci.yml"}]},{"bom-ref":"pkg:github/actions/setup-node@v3?package-id=dc6c950c7c10e2fa","type":"library","name":"actions/setup-node","version":"v3","cpe":"cpe:2.3:a:actions\\/setup-node:actions\\/setup-node:v3:*:*:*:*:*:*:*","purl":"pkg:github/actions/setup-node@v3","properties":[{"name":"syft:package:foundBy","value":"github-actions-usage-cataloger"},{"name":"syft:package:type","value":"github-action"},{"name":"syft:package:metadataType","value":"github-actions-use-statement"},{"name":"syft:cpe23","value":"cpe:2.3:a:actions\\/setup-node:actions\\/setup_node:v3:*:*:*:*:*:*:*"},{"name":"syft:cpe23","value":"cpe:2.3:a:actions\\/setup_node:actions\\/setup-node:v3:*:*:*:*:*:*:*"},{"name":"syft:cpe23","value":"cpe:2.3:a:actions\\/setup_node:actions\\/setup_node:v3:*:*:*:*:*:*:*"},{"name":"syft:cpe23","value":"cpe:2.3:a:actions\\/setup:actions\\/setup-node:v3:*:*:*:*:*:*:*"},{"name":"syft:cpe23","value":"cpe:2.3:a:actions\\/setup:actions\\/setup_node:v3:*:*:*:*:*:*:*"},{"name":"syft:location:0:path","value":"/node_modules/string.prototype.includes/.github/workflows/publish-on-tag.yml"}]},{"bom-ref":"pkg:github/actions/setup-node@v4?package-id=de6527b74c32bd7a","type":"library","name":"actions/setup-node","version":"v4","cpe":"cpe:2.3:a:actions\\/setup-node:actions\\/setup-node:v4:*:*:*:*:*:*:*","purl":"pkg:github/actions/setup-node@v4","properties":[{"name":"syft:package:foundBy","value":"github-actions-usage-cataloger"},{"name":"syft:package:type","value":"github-action"},{"name":"syft:package:metadataType","value":"github-actions-use-statement"},{"name":"syft:cpe23","value":"cpe:2.3:a:actions\\/setup-node:actions\\/setup_node:v4:*:*:*:*:*:*:*"},{"name":"syft:cpe23","value":"cpe:2.3:a:actions\\/setup_node:actions\\/setup-node:v4:*:*:*:*:*:*:*"},{"name":"syft:cpe23","value":"cpe:2.3:a:actions\\/setup_node:actions\\/setup_node:v4:*:*:*:*:*:*:*"},{"name":"syft:cpe23","value":"cpe:2.3:a:actions\\/setup:actions\\/setup-node:v4:*:*:*:*:*:*:*"},{"name":"syft:cpe23","value":"cpe:2.3:a:actions\\/setup:actions\\/setup_node:v4:*:*:*:*:*:*:*"},{"name":"syft:location:0:path","value":"/node_modules/reusify/.github/workflows/ci.yml"}]},{"bom-ref":"pkg:npm/caniuse-lite@1.0.30001754?package-id=e52918ad5c1bcdd5","type":"library","name":"caniuse-lite","version":"1.0.30001754","licenses":[{"license":{"id":"CC-BY-4.0"}}],"cpe":"cpe:2.3:a:caniuse-lite:caniuse-lite:1.0.30001754:*:*:*:*:*:*:*","purl":"pkg:npm/caniuse-lite@1.0.30001754","properties":[{"name":"syft:package:foundBy","value":"javascript-lock-cataloger"},{"name":"syft:package:language","value":"javascript"},{"name":"syft:package:type","value":"npm"},{"name":"syft:package:metadataType","value":"javascript-npm-package-lock-entry"},{"name":"syft:cpe23","value":"cpe:2.3:a:caniuse-lite:caniuse_lite:1.0.30001754:*:*:*:*:*:*:*"},{"name":"syft:cpe23","value":"cpe:2.3:a:caniuse_lite:caniuse-lite:1.0.30001754:*:*:*:*:*:*:*"},{"name":"syft:cpe23","value":"cpe:2.3:a:caniuse_lite:caniuse_lite:1.0.30001754:*:*:*:*:*:*:*"},{"name":"syft:cpe23","value":"cpe:2.3:a:caniuse:caniuse-lite:1.0.30001754:*:*:*:*:*:*:*"},{"name":"syft:cpe23","value":"cpe:2.3:a:caniuse:caniuse_lite:1.0.30001754:*:*:*:*:*:*:*"},{"name":"syft:location:0:path","value":"/package-lock.json"}]},{"bom-ref":"pkg:npm/client-only@0.0.1?package-id=f9ca5fb0d7b2ac77","type":"library","name":"client-only","version":"0.0.1","licenses":[{"license":{"id":"MIT"}}],"cpe":"cpe:2.3:a:client-only:client-only:0.0.1:*:*:*:*:*:*:*","purl":"pkg:npm/client-only@0.0.1","properties":[{"name":"syft:package:foundBy","value":"javascript-lock-cataloger"},{"name":"syft:package:language","value":"javascript"},{"name":"syft:package:type","value":"npm"},{"name":"syft:package:metadataType","value":"javascript-npm-package-lock-entry"},{"name":"syft:cpe23","value":"cpe:2.3:a:client-only:client_only:0.0.1:*:*:*:*:*:*:*"},{"name":"syft:cpe23","value":"cpe:2.3:a:client_only:client-only:0.0.1:*:*:*:*:*:*:*"},{"name":"syft:cpe23","value":"cpe:2.3:a:client_only:client_only:0.0.1:*:*:*:*:*:*:*"},{"name":"syft:cpe23","value":"cpe:2.3:a:client:client-only:0.0.1:*:*:*:*:*:*:*"},{"name":"syft:cpe23","value":"cpe:2.3:a:client:client_only:0.0.1:*:*:*:*:*:*:*"},{"name":"syft:location:0:path","value":"/package-lock.json"}]},{"bom-ref":"pkg:npm/detect-libc@2.1.2?package-id=12c807e8192beeba","type":"library","name":"detect-libc","version":"2.1.2","licenses":[{"license":{"id":"Apache-2.0"}}],"cpe":"cpe:2.3:a:detect-libc:detect-libc:2.1.2:*:*:*:*:*:*:*","purl":"pkg:npm/detect-libc@2.1.2","properties":[{"name":"syft:package:foundBy","value":"javascript-lock-cataloger"},{"name":"syft:package:language","value":"javascript"},{"name":"syft:package:type","value":"npm"},{"name":"syft:package:metadataType","value":"javascript-npm-package-lock-entry"},{"name":"syft:cpe23","value":"cpe:2.3:a:detect-libc:detect_libc:2.1.2:*:*:*:*:*:*:*"},{"name":"syft:cpe23","value":"cpe:2.3:a:detect_libc:detect-libc:2.1.2:*:*:*:*:*:*:*"},{"name":"syft:cpe23","value":"cpe:2.3:a:detect_libc:detect_libc:2.1.2:*:*:*:*:*:*:*"},{"name":"syft:cpe23","value":"cpe:2.3:a:detect:detect-libc:2.1.2:*:*:*:*:*:*:*"},{"name":"syft:cpe23","value":"cpe:2.3:a:detect:detect_libc:2.1.2:*:*:*:*:*:*:*"},{"name":"syft:location:0:path","value":"/package-lock.json"}]},{"bom-ref":"pkg:npm/grc-frontend-portal@0.1.0?package-id=7d8b25d4deebb1cc","type":"library","name":"grc-frontend-portal","version":"0.1.0","cpe":"cpe:2.3:a:grc-frontend-portal:grc-frontend-portal:0.1.0:*:*:*:*:*:*:*","purl":"pkg:npm/grc-frontend-portal@0.1.0","properties":[{"name":"syft:package:foundBy","value":"javascript-lock-cataloger"},{"name":"syft:package:language","value":"javascript"},{"name":"syft:package:type","value":"npm"},{"name":"syft:package:metadataType","value":"javascript-npm-package-lock-entry"},{"name":"syft:cpe23","value":"cpe:2.3:a:grc-frontend-portal:grc_frontend_portal:0.1.0:*:*:*:*:*:*:*"},{"name":"syft:cpe23","value":"cpe:2.3:a:grc_frontend_portal:grc-frontend-portal:0.1.0:*:*:*:*:*:*:*"},{"name":"syft:cpe23","value":"cpe:2.3:a:grc_frontend_portal:grc_frontend_portal:0.1.0:*:*:*:*:*:*:*"},{"name":"syft:cpe23","value":"cpe:2.3:a:grc-frontend:grc-frontend-portal:0.1.0:*:*:*:*:*:*:*"},{"name":"syft:cpe23","value":"cpe:2.3:a:grc-frontend:grc_frontend_portal:0.1.0:*:*:*:*:*:*:*"},{"name":"syft:cpe23","value":"cpe:2.3:a:grc_frontend:grc-frontend-portal:0.1.0:*:*:*:*:*:*:*"},{"name":"syft:cpe23","value":"cpe:2.3:a:grc_frontend:grc_frontend_portal:0.1.0:*:*:*:*:*:*:*"},{"name":"syft:cpe23","value":"cpe:2.3:a:grc:grc-frontend-portal:0.1.0:*:*:*:*:*:*:*"},{"name":"syft:cpe23","value":"cpe:2.3:a:grc:grc_frontend_portal:0.1.0:*:*:*:*:*:*:*"},{"name":"syft:location:0:path","value":"/package-lock.json"}]},{"bom-ref":"pkg:github/ljharb/actions@main?package-id=8810565e23c7d046#.github/workflows/node.yml","type":"library","name":"ljharb/actions/.github/workflows/node.yml","version":"main","cpe":"cpe:2.3:a:ljharb\\/actions\\/.github\\/workflows\\/node.yml:ljharb\\/actions\\/.github\\/workflows\\/node.yml:main:*:*:*:*:*:*:*","purl":"pkg:github/ljharb/actions@main#.github/workflows/node.yml","properties":[{"name":"syft:package:foundBy","value":"github-action-workflow-usage-cataloger"},{"name":"syft:package:type","value":"github-action-workflow"},{"name":"syft:package:metadataType","value":"github-actions-use-statement"},{"name":"syft:location:0:path","value":"/node_modules/string.prototype.includes/.github/workflows/node-aught.yml"}]},{"bom-ref":"pkg:github/ljharb/actions@main?package-id=cac9ad16d5e92084#.github/workflows/node.yml","type":"library","name":"ljharb/actions/.github/workflows/node.yml","version":"main","cpe":"cpe:2.3:a:ljharb\\/actions\\/.github\\/workflows\\/node.yml:ljharb\\/actions\\/.github\\/workflows\\/node.yml:main:*:*:*:*:*:*:*","purl":"pkg:github/ljharb/actions@main#.github/workflows/node.yml","properties":[{"name":"syft:package:foundBy","value":"github-action-workflow-usage-cataloger"},{"name":"syft:package:type","value":"github-action-workflow"},{"name":"syft:package:metadataType","value":"github-actions-use-statement"},{"name":"syft:location:0:path","value":"/node_modules/string.prototype.includes/.github/workflows/node-tens.yml"}]},{"bom-ref":"pkg:github/ljharb/actions@main?package-id=9d5538e22d6bc08d#.github/workflows/pretest.yml","type":"library","name":"ljharb/actions/.github/workflows/pretest.yml","version":"main","cpe":"cpe:2.3:a:ljharb\\/actions\\/.github\\/workflows\\/pretest.yml:ljharb\\/actions\\/.github\\/workflows\\/pretest.yml:main:*:*:*:*:*:*:*","purl":"pkg:github/ljharb/actions@main#.github/workflows/pretest.yml","properties":[{"name":"syft:package:foundBy","value":"github-action-workflow-usage-cataloger"},{"name":"syft:package:type","value":"github-action-workflow"},{"name":"syft:package:metadataType","value":"github-actions-use-statement"},{"name":"syft:location:0:path","value":"/node_modules/string.prototype.includes/.github/workflows/node-pretest.yml"}]},{"bom-ref":"pkg:github/ljharb/actions@main?package-id=c189b4bc63e99716#.github/workflows/rebase.yml","type":"library","name":"ljharb/actions/.github/workflows/rebase.yml","version":"main","cpe":"cpe:2.3:a:ljharb\\/actions\\/.github\\/workflows\\/rebase.yml:ljharb\\/actions\\/.github\\/workflows\\/rebase.yml:main:*:*:*:*:*:*:*","purl":"pkg:github/ljharb/actions@main#.github/workflows/rebase.yml","properties":[{"name":"syft:package:foundBy","value":"github-action-workflow-usage-cataloger"},{"name":"syft:package:type","value":"github-action-workflow"},{"name":"syft:package:metadataType","value":"github-actions-use-statement"},{"name":"syft:location:0:path","value":"/node_modules/string.prototype.includes/.github/workflows/rebase.yml"}]},{"bom-ref":"pkg:github/ljharb/require-allow-edits@main?package-id=c8c151dccb92486f","type":"library","name":"ljharb/require-allow-edits","version":"main","cpe":"cpe:2.3:a:ljharb\\/require-allow-edits:ljharb\\/require-allow-edits:main:*:*:*:*:*:*:*","purl":"pkg:github/ljharb/require-allow-edits@main","properties":[{"name":"syft:package:foundBy","value":"github-actions-usage-cataloger"},{"name":"syft:package:type","value":"github-action"},{"name":"syft:package:metadataType","value":"github-actions-use-statement"},{"name":"syft:cpe23","value":"cpe:2.3:a:ljharb\\/require-allow-edits:ljharb\\/require_allow_edits:main:*:*:*:*:*:*:*"},{"name":"syft:cpe23","value":"cpe:2.3:a:ljharb\\/require_allow_edits:ljharb\\/require-allow-edits:main:*:*:*:*:*:*:*"},{"name":"syft:cpe23","value":"cpe:2.3:a:ljharb\\/require_allow_edits:ljharb\\/require_allow_edits:main:*:*:*:*:*:*:*"},{"name":"syft:cpe23","value":"cpe:2.3:a:ljharb\\/require-allow:ljharb\\/require-allow-edits:main:*:*:*:*:*:*:*"},{"name":"syft:cpe23","value":"cpe:2.3:a:ljharb\\/require-allow:ljharb\\/require_allow_edits:main:*:*:*:*:*:*:*"},{"name":"syft:cpe23","value":"cpe:2.3:a:ljharb\\/require_allow:ljharb\\/require-allow-edits:main:*:*:*:*:*:*:*"},{"name":"syft:cpe23","value":"cpe:2.3:a:ljharb\\/require_allow:ljharb\\/require_allow_edits:main:*:*:*:*:*:*:*"},{"name":"syft:cpe23","value":"cpe:2.3:a:ljharb\\/require:ljharb\\/require-allow-edits:main:*:*:*:*:*:*:*"},{"name":"syft:cpe23","value":"cpe:2.3:a:ljharb\\/require:ljharb\\/require_allow_edits:main:*:*:*:*:*:*:*"},{"name":"syft:location:0:path","value":"/node_modules/string.prototype.includes/.github/workflows/require-allow-edits.yml"}]},{"bom-ref":"pkg:npm/nanoid@3.3.11?package-id=f2580c79e34e47d5","type":"library","name":"nanoid","version":"3.3.11","licenses":[{"license":{"id":"MIT"}}],"cpe":"cpe:2.3:a:nanoid_project:nanoid:3.3.11:*:*:*:*:node.js:*:*","purl":"pkg:npm/nanoid@3.3.11","properties":[{"name":"syft:package:foundBy","value":"javascript-lock-cataloger"},{"name":"syft:package:language","value":"javascript"},{"name":"syft:package:type","value":"npm"},{"name":"syft:package:metadataType","value":"javascript-npm-package-lock-entry"},{"name":"syft:location:0:path","value":"/package-lock.json"}]},{"bom-ref":"pkg:npm/next@16.0.1?package-id=9f5c6dac158dd279","type":"library","name":"next","version":"16.0.1","licenses":[{"license":{"id":"MIT"}}],"cpe":"cpe:2.3:a:next:next:16.0.1:*:*:*:*:*:*:*","purl":"pkg:npm/next@16.0.1","properties":[{"name":"syft:package:foundBy","value":"javascript-lock-cataloger"},{"name":"syft:package:language","value":"javascript"},{"name":"syft:package:type","value":"npm"},{"name":"syft:package:metadataType","value":"javascript-npm-package-lock-entry"},{"name":"syft:location:0:path","value":"/package-lock.json"}]},{"bom-ref":"pkg:npm/picocolors@1.1.1?package-id=473a71d1686a81db","type":"library","name":"picocolors","version":"1.1.1","licenses":[{"license":{"id":"ISC"}}],"cpe":"cpe:2.3:a:picocolors:picocolors:1.1.1:*:*:*:*:*:*:*","purl":"pkg:npm/picocolors@1.1.1","properties":[{"name":"syft:package:foundBy","value":"javascript-lock-cataloger"},{"name":"syft:package:language","value":"javascript"},{"name":"syft:package:type","value":"npm"},{"name":"syft:package:metadataType","value":"javascript-npm-package-lock-entry"},{"name":"syft:location:0:path","value":"/package-lock.json"}]},{"bom-ref":"pkg:npm/playwright@1.56.1?package-id=fb42b62387f98891","type":"library","name":"playwright","version":"1.56.1","licenses":[{"license":{"id":"Apache-2.0"}}],"cpe":"cpe:2.3:a:playwright:playwright:1.56.1:*:*:*:*:*:*:*","purl":"pkg:npm/playwright@1.56.1","properties":[{"name":"syft:package:foundBy","value":"javascript-lock-cataloger"},{"name":"syft:package:language","value":"javascript"},{"name":"syft:package:type","value":"npm"},{"name":"syft:package:metadataType","value":"javascript-npm-package-lock-entry"},{"name":"syft:location:0:path","value":"/package-lock.json"}]},{"bom-ref":"pkg:npm/playwright-core@1.56.1?package-id=a6f01ccb2c52e336","type":"library","name":"playwright-core","version":"1.56.1","licenses":[{"license":{"id":"Apache-2.0"}}],"cpe":"cpe:2.3:a:playwright-core:playwright-core:1.56.1:*:*:*:*:*:*:*","purl":"pkg:npm/playwright-core@1.56.1","properties":[{"name":"syft:package:foundBy","value":"javascript-lock-cataloger"},{"name":"syft:package:language","value":"javascript"},{"name":"syft:package:type","value":"npm"},{"name":"syft:package:metadataType","value":"javascript-npm-package-lock-entry"},{"name":"syft:cpe23","value":"cpe:2.3:a:playwright-core:playwright_core:1.56.1:*:*:*:*:*:*:*"},{"name":"syft:cpe23","value":"cpe:2.3:a:playwright_core:playwright-core:1.56.1:*:*:*:*:*:*:*"},{"name":"syft:cpe23","value":"cpe:2.3:a:playwright_core:playwright_core:1.56.1:*:*:*:*:*:*:*"},{"name":"syft:cpe23","value":"cpe:2.3:a:playwright:playwright-core:1.56.1:*:*:*:*:*:*:*"},{"name":"syft:cpe23","value":"cpe:2.3:a:playwright:playwright_core:1.56.1:*:*:*:*:*:*:*"},{"name":"syft:location:0:path","value":"/package-lock.json"}]},{"bom-ref":"pkg:npm/postcss@8.4.31?package-id=3dc0ce709442ca21","type":"library","name":"postcss","version":"8.4.31","licenses":[{"license":{"id":"MIT"}}],"cpe":"cpe:2.3:a:postcss:postcss:8.4.31:*:*:*:*:node.js:*:*","purl":"pkg:npm/postcss@8.4.31","properties":[{"name":"syft:package:foundBy","value":"javascript-lock-cataloger"},{"name":"syft:package:language","value":"javascript"},{"name":"syft:package:type","value":"npm"},{"name":"syft:package:metadataType","value":"javascript-npm-package-lock-entry"},{"name":"syft:location:0:path","value":"/package-lock.json"}]},{"bom-ref":"pkg:npm/react@19.2.0?package-id=9b06f1ad1fca7e8e","type":"library","name":"react","version":"19.2.0","licenses":[{"license":{"id":"MIT"}}],"cpe":"cpe:2.3:a:react:react:19.2.0:*:*:*:*:*:*:*","purl":"pkg:npm/react@19.2.0","properties":[{"name":"syft:package:foundBy","value":"javascript-lock-cataloger"},{"name":"syft:package:language","value":"javascript"},{"name":"syft:package:type","value":"npm"},{"name":"syft:package:metadataType","value":"javascript-npm-package-lock-entry"},{"name":"syft:location:0:path","value":"/package-lock.json"}]},{"bom-ref":"pkg:npm/react-dom@19.2.0?package-id=64f8ff87020d016d","type":"library","name":"react-dom","version":"19.2.0","licenses":[{"license":{"id":"MIT"}}],"cpe":"cpe:2.3:a:react-dom:react-dom:19.2.0:*:*:*:*:*:*:*","purl":"pkg:npm/react-dom@19.2.0","properties":[{"name":"syft:package:foundBy","value":"javascript-lock-cataloger"},{"name":"syft:package:language","value":"javascript"},{"name":"syft:package:type","value":"npm"},{"name":"syft:package:metadataType","value":"javascript-npm-package-lock-entry"},{"name":"syft:cpe23","value":"cpe:2.3:a:react-dom:react_dom:19.2.0:*:*:*:*:*:*:*"},{"name":"syft:cpe23","value":"cpe:2.3:a:react_dom:react-dom:19.2.0:*:*:*:*:*:*:*"},{"name":"syft:cpe23","value":"cpe:2.3:a:react_dom:react_dom:19.2.0:*:*:*:*:*:*:*"},{"name":"syft:cpe23","value":"cpe:2.3:a:react:react-dom:19.2.0:*:*:*:*:*:*:*"},{"name":"syft:cpe23","value":"cpe:2.3:a:react:react_dom:19.2.0:*:*:*:*:*:*:*"},{"name":"syft:location:0:path","value":"/package-lock.json"}]},{"bom-ref":"pkg:npm/scheduler@0.27.0?package-id=d8a7a93e3c289b34","type":"library","name":"scheduler","version":"0.27.0","licenses":[{"license":{"id":"MIT"}}],"cpe":"cpe:2.3:a:scheduler:scheduler:0.27.0:*:*:*:*:*:*:*","purl":"pkg:npm/scheduler@0.27.0","properties":[{"name":"syft:package:foundBy","value":"javascript-lock-cataloger"},{"name":"syft:package:language","value":"javascript"},{"name":"syft:package:type","value":"npm"},{"name":"syft:package:metadataType","value":"javascript-npm-package-lock-entry"},{"name":"syft:location:0:path","value":"/package-lock.json"}]},{"bom-ref":"pkg:npm/semver@7.7.3?package-id=de21ae235570ab4f","type":"library","name":"semver","version":"7.7.3","licenses":[{"license":{"id":"ISC"}}],"cpe":"cpe:2.3:a:npmjs:semver:7.7.3:*:*:*:*:node.js:*:*","purl":"pkg:npm/semver@7.7.3","properties":[{"name":"syft:package:foundBy","value":"javascript-lock-cataloger"},{"name":"syft:package:language","value":"javascript"},{"name":"syft:package:type","value":"npm"},{"name":"syft:package:metadataType","value":"javascript-npm-package-lock-entry"},{"name":"syft:location:0:path","value":"/package-lock.json"}]},{"bom-ref":"pkg:npm/sharp@0.34.5?package-id=4c1a85686cff7223","type":"library","name":"sharp","version":"0.34.5","licenses":[{"license":{"id":"Apache-2.0"}}],"cpe":"cpe:2.3:a:sharp_project:sharp:0.34.5:*:*:*:*:node.js:*:*","purl":"pkg:npm/sharp@0.34.5","properties":[{"name":"syft:package:foundBy","value":"javascript-lock-cataloger"},{"name":"syft:package:language","value":"javascript"},{"name":"syft:package:type","value":"npm"},{"name":"syft:package:metadataType","value":"javascript-npm-package-lock-entry"},{"name":"syft:location:0:path","value":"/package-lock.json"}]},{"bom-ref":"pkg:npm/source-map-js@1.2.1?package-id=580e047d095b71d2","type":"library","name":"source-map-js","version":"1.2.1","licenses":[{"license":{"id":"BSD-3-Clause"}}],"cpe":"cpe:2.3:a:source-map-js:source-map-js:1.2.1:*:*:*:*:*:*:*","purl":"pkg:npm/source-map-js@1.2.1","properties":[{"name":"syft:package:foundBy","value":"javascript-lock-cataloger"},{"name":"syft:package:language","value":"javascript"},{"name":"syft:package:type","value":"npm"},{"name":"syft:package:metadataType","value":"javascript-npm-package-lock-entry"},{"name":"syft:cpe23","value":"cpe:2.3:a:source-map-js:source_map_js:1.2.1:*:*:*:*:*:*:*"},{"name":"syft:cpe23","value":"cpe:2.3:a:source_map_js:source-map-js:1.2.1:*:*:*:*:*:*:*"},{"name":"syft:cpe23","value":"cpe:2.3:a:source_map_js:source_map_js:1.2.1:*:*:*:*:*:*:*"},{"name":"syft:cpe23","value":"cpe:2.3:a:source-map:source-map-js:1.2.1:*:*:*:*:*:*:*"},{"name":"syft:cpe23","value":"cpe:2.3:a:source-map:source_map_js:1.2.1:*:*:*:*:*:*:*"},{"name":"syft:cpe23","value":"cpe:2.3:a:source_map:source-map-js:1.2.1:*:*:*:*:*:*:*"},{"name":"syft:cpe23","value":"cpe:2.3:a:source_map:source_map_js:1.2.1:*:*:*:*:*:*:*"},{"name":"syft:cpe23","value":"cpe:2.3:a:source:source-map-js:1.2.1:*:*:*:*:*:*:*"},{"name":"syft:cpe23","value":"cpe:2.3:a:source:source_map_js:1.2.1:*:*:*:*:*:*:*"},{"name":"syft:location:0:path","value":"/package-lock.json"}]},{"bom-ref":"pkg:npm/styled-jsx@5.1.6?package-id=1b3078b71fadf83b","type":"library","name":"styled-jsx","version":"5.1.6","licenses":[{"license":{"id":"MIT"}}],"cpe":"cpe:2.3:a:styled-jsx:styled-jsx:5.1.6:*:*:*:*:*:*:*","purl":"pkg:npm/styled-jsx@5.1.6","properties":[{"name":"syft:package:foundBy","value":"javascript-lock-cataloger"},{"name":"syft:package:language","value":"javascript"},{"name":"syft:package:type","value":"npm"},{"name":"syft:package:metadataType","value":"javascript-npm-package-lock-entry"},{"name":"syft:cpe23","value":"cpe:2.3:a:styled-jsx:styled_jsx:5.1.6:*:*:*:*:*:*:*"},{"name":"syft:cpe23","value":"cpe:2.3:a:styled_jsx:styled-jsx:5.1.6:*:*:*:*:*:*:*"},{"name":"syft:cpe23","value":"cpe:2.3:a:styled_jsx:styled_jsx:5.1.6:*:*:*:*:*:*:*"},{"name":"syft:cpe23","value":"cpe:2.3:a:styled:styled-jsx:5.1.6:*:*:*:*:*:*:*"},{"name":"syft:cpe23","value":"cpe:2.3:a:styled:styled_jsx:5.1.6:*:*:*:*:*:*:*"},{"name":"syft:location:0:path","value":"/package-lock.json"}]},{"bom-ref":"pkg:npm/tslib@2.8.1?package-id=e1e89d1b3e4c6f9a","type":"library","name":"tslib","version":"2.8.1","licenses":[{"license":{"id":"0BSD"}}],"cpe":"cpe:2.3:a:tslib:tslib:2.8.1:*:*:*:*:*:*:*","purl":"pkg:npm/tslib@2.8.1","properties":[{"name":"syft:package:foundBy","value":"javascript-lock-cataloger"},{"name":"syft:package:language","value":"javascript"},{"name":"syft:package:type","value":"npm"},{"name":"syft:package:metadataType","value":"javascript-npm-package-lock-entry"},{"name":"syft:location:0:path","value":"/package-lock.json"}]},{"bom-ref":"28c718f924e0e3af","type":"file","name":"/Users/jimmy/dev/compliance/grc-frontend-portal/node_modules/fastq/.github/workflows/ci.yml","hashes":[{"alg":"SHA-1","content":"6d2fb0eb7e693f9697f4945e992728a74710378d"},{"alg":"SHA-256","content":"c8c1b113b0e393b0f55e01edd953a2fdda6744de835752043e3051299878c705"}]},{"bom-ref":"7eee1dce79d34bd0","type":"file","name":"/Users/jimmy/dev/compliance/grc-frontend-portal/node_modules/reusify/.github/workflows/ci.yml","hashes":[{"alg":"SHA-1","content":"46a64a3a41de42fb7efbab61e8c8662f8181e602"},{"alg":"SHA-256","content":"2518554c9d38a88c89d09c005367745909dc55db127560856cb044abbe698117"}]},{"bom-ref":"f1956826a3144dfd","type":"file","name":"/Users/jimmy/dev/compliance/grc-frontend-portal/node_modules/string.prototype.includes/.github/workflows/node-aught.yml","hashes":[{"alg":"SHA-1","content":"7a258c0636b8a1d8f53da5536031cfbc08b7cf7b"},{"alg":"SHA-256","content":"5871ef48364580ac031a5a81168c83db925ec5ebfceccc7724ebbf2d94c1cb33"}]},{"bom-ref":"0756a503541912b6","type":"file","name":"/Users/jimmy/dev/compliance/grc-frontend-portal/node_modules/string.prototype.includes/.github/workflows/node-pretest.yml","hashes":[{"alg":"SHA-1","content":"2aaddb6d5e0ee572e06eea89e1753be6c538113a"},{"alg":"SHA-256","content":"9676fb4a58c661a95ed005a4d230f7c645064522de8dd15084ff168978f55b16"}]},{"bom-ref":"cfd6c9ae577b468b","type":"file","name":"/Users/jimmy/dev/compliance/grc-frontend-portal/node_modules/string.prototype.includes/.github/workflows/node-tens.yml","hashes":[{"alg":"SHA-1","content":"88f7942b3b868ce3d6710c7b149939df840db334"},{"alg":"SHA-256","content":"d4c4e50d7d59a176e660bb414ade5d71093a2eb436238d7be5c85e02ee527a2b"}]},{"bom-ref":"95d085dc6937d5ad","type":"file","name":"/Users/jimmy/dev/compliance/grc-frontend-portal/node_modules/string.prototype.includes/.github/workflows/publish-on-tag.yml","hashes":[{"alg":"SHA-1","content":"5ef1efa6ccdafc2d43b396189bf96e10922470fd"},{"alg":"SHA-256","content":"640bd6e639fd2413bc269324a3adc26e0f204fd9b74d9b2bc9b0e48a25b80f8f"}]},{"bom-ref":"de47be8eb2859930","type":"file","name":"/Users/jimmy/dev/compliance/grc-frontend-portal/node_modules/string.prototype.includes/.github/workflows/rebase.yml","hashes":[{"alg":"SHA-1","content":"5389804d431cf69d9b2e8cbb28b73cc1cf7df550"},{"alg":"SHA-256","content":"bf240e1af684b508938a402d06d8e8dcd424dde3934f68f4a99327856a2e383c"}]},{"bom-ref":"413e34720b1eab90","type":"file","name":"/Users/jimmy/dev/compliance/grc-frontend-portal/node_modules/string.prototype.includes/.github/workflows/require-allow-edits.yml","hashes":[{"alg":"SHA-1","content":"10d8fed72f984a910237b1cfb0e00f93749c3a9e"},{"alg":"SHA-256","content":"b892e4ab2b49f3b2e255c51e96d92070b0fd968d4a42307ed6b7f18c7cda820b"}]},{"bom-ref":"fd71c2238fc07657","type":"file","name":"/Users/jimmy/dev/compliance/grc-frontend-portal/package-lock.json","hashes":[{"alg":"SHA-1","content":"fc89964da29c7d7b3f88c075365c5e49bac69e1f"},{"alg":"SHA-256","content":"f19e67574f6907a204f1e12070a7487a69c20c398f27dcd6c68f322ec205e033"}]}]}
